Workbook

Sheet Resumen
A1: PORTAFOLIO SVU — DASHBOARD
A2: Actualizado al: | B2: =TODAY()
A4: Tipo de cambio USD/CLP (referencia): | B4: 921.42 | I4: Tope cripto: | J4: 0.15
A6: ASIGNACIÓN POR CATEGORÍA — REAL vs. OBJETIVO
A7: Categoría | B7: Monto CLP | C7: % Real | D7: % Objetivo | E7: Diferencia | F7: Estado | G7: Tope máx.
A8: Dividendos | B8: =SUMIF('Cartera Detalle'!$B:$B,A8,'Cartera Detalle'!$H:$H) | C8: =B8/$B$13 | D8: 0.7 | E8: =C8-D8 | F8: =IF(ABS(E8)<=0.03,"OK","Desviado")
A9: USA | B9: =SUMIF('Cartera Detalle'!$B:$B,A9,'Cartera Detalle'!$H:$H) | C9: =B9/$B$13 | D9: 0.075 | E9: =C9-D9 | F9: =IF(ABS(E9)<=0.03,"OK","Desviado")
A10: Emergentes | B10: =SUMIF('Cartera Detalle'!$B:$B,A10,'Cartera Detalle'!$H:$H) | C10: =B10/$B$13 | D10: 0.075 | E10: =C10-D10 | F10: =IF(ABS(E10)<=0.03,"OK","Desviado")
A11: Internacional | B11: =SUMIF('Cartera Detalle'!$B:$B,A11,'Cartera Detalle'!$H:$H) | C11: =B11/$B$13 | D11: 0.075 | E11: =C11-D11 | F11: =IF(ABS(E11)<=0.03,"OK","Desviado")
A12: Crypto | B12: =SUMIF('Cartera Detalle'!$B:$B,A12,'Cartera Detalle'!$H:$H) | C12: =B12/$B$13 | D12: 0.075 | E12: =C12-D12 | F12: =IF(C12>$G$12,"⚠ SOBRE TOPE",IF(ABS(E12)<=0.03,"OK","Desviado")) | G12: 15%
A13: TOTAL PORTAFOLIO | B13: =SUM(B8:B12) | C13: =B13/B13
A15: CONCENTRACIÓN POR EMPRESA — TOP POSICIONES
A16: Empresa | B16: % del Portafolio | C16: Tope individual | D16: Estado
A17: (ver columna % Portafolio en 'Cartera Detalle' — ordenar de mayor a menor)
A18: Tope individual por empresa: | B18: 0.3
A20: META DE INGRESO PASIVO
A21: Concepto | B21: Valor
A22: Meta ingreso pasivo mensual (pesos de hoy) | B22: 2000000
A23: Edad objetivo de independencia | B23: 60
A24: Fecha objetivo | B24: 15/02/2057
A26: Ingreso pasivo proyectado a esa fecha (CLP/mes): ver hoja 'Proyección Anual'

Sheet IPS - Reglas
A1: DECLARACIÓN DE POLÍTICA DE INVERSIÓN (IPS) — Sebastián Viveros Uribe
B3: 1. OBJETIVO
B4: Construir un flujo de ingreso pasivo creciente (dividendos) para alcanzar independencia financiera frente a ingresos inestables.
B5: Meta: $2.000.000+ CLP/mes (en pesos de hoy) de ingreso pasivo a la edad de 60 años (15/02/2057).
B6: Horizonte de inversión: ~31 años. La volatilidad de precio NO es la preocupación principal; el deterioro permanente del negocio sí lo es.
B8: 2. ASIGNACIÓN OBJETIVO (para aportes nuevos)
B9: 70% Dividendos — acciones y ETF/CFI chilenos enfocados en dividendo (incl. REITs tipo CFINRENTAS).
B10: 30% repartido en partes iguales (7,5% c/u) entre: USA, Emergentes, Internacional desarrollado y Criptomonedas.
B11: El rebalanceo es PASIVO: no se vende para reequilibrar. Si una categoría supera su tope, los aportes nuevos dejan de destinarse ahí y se redistribuyen al resto hasta que vuelva a estar dentro del rango.
B13: 3. TOPES DE CONCENTRACIÓN (LÍMITES DUROS)
B14: • Máximo por empresa individual: 30% del portafolio total. Si una posición (ej. Banco de Chile) supera este nivel, no se compra más de esa empresa con aportes nuevos.
B15: • Máximo en Criptomonedas: 15% del portafolio total. Sobre ese nivel, los aportes destinados a cripto se redirigen a las otras 4 categorías.
B16: • Posiciones de riesgo regulatorio/concesión única (ej. ZOFRI): aunque no haya un tope numérico fijado, revisar explícitamente el riesgo de ley/concesión en cada revisión semestral (ver hoja Tesis).
... B39: Esta evaluación debe iniciarse CON ANTICIPACIÓN (idealmente 1-2 años antes de necesitarla), no de forma reactiva al cambio de tramo impositivo, para estructurar correctamente el aporte de activos como reorganización empresarial y evitar gatillar impuesto a la ganancia de capital en el traspaso.

Sheet Cartera Detalle
A1: CARTERA DETALLE — registro maestro (ingresa Precio Actual y Divs Acum.; el resto se calcula solo)
A3: Instrumento | B3: Categoría | C3: Broker | D3: Cantidad | E3: Precio Compra | F3: Precio Actual | G3: Costo Total (CLP) | H3: Valor Mercado (CLP) | I3: Divs Acum. (CLP) | J3: Rentabilidad | K3: Notas | L3: % Portafolio
A4: CFISPETF (ETF S&P 500) | B4: USA | C4: Itaú | D4: 240 | E4: 1492.2708 | F4: 1721.1 | G4: 358144.99 | H4: 413064 | I4: 58 | J4: =IF(G4=0,"",(H4+I4-G4)/G4) | L4: =H4/$H$19
A5: CFINRENTAS (Rentas Inmob.) | B5: Dividendos | C5: Itaú | D5: 88 | E5: 1702.977 | F5: 2198.34 | G5: 149861.98 | H5: 193453.92 | I5: 12381 | J5: =IF(G5=0,"",(H5+I5-G5)/G5) | L5: =H5/$H$19
A6: CFMITNIPSA (ETF IPSA) | B6: Dividendos | C6: Itaú | D6: 24 | E6: 3964.375 | F6: 4988.1 | G6: 95145 | H6: 119714.4 | I6: 3605 | J6: =IF(G6=0,"",(H6+I6-G6)/G6) | L6: =H6/$H$19
A7: CFINASDAQ (ETF Nasdaq 100) | B7: USA | C7: Itaú | D7: 27 | E7: 1800 | F7: 2153.2 | G7: 48600 | H7: 58136.4 | I7: 0 | J7: =IF(G7=0,"",(H7+I7-G7)/G7) | L7: =H7/$H$19
A8: Caja + Div. por liquidar (Itaú) | C8: Itaú | H8: 1745 | I8: 0 | J8: =IF(G8=0,"",(H8+I8-G8)/G8) | L8: =H8/$H$19
A9: CHILE (Banco de Chile) | B9: Dividendos | C9: Trii + Zesty | D9: 576 | E9: 159.0818 | F9: 177.8 | G9: 91631.11 | H9: 102412.8 | I9: 0 | J9: =IF(G9=0,"",(H9+I9-G9)/G9) | L9: =H9/$H$19
A10: ZOFRI | B10: Dividendos | C10: Zesty | D10: 99 | E10: 1008 | F10: 990.3434 | G10: 99792 | H10: 98044 | I10: 0 | J10: =IF(G10=0,"",(H10+I10-G10)/G10) | L10: =H10/$H$19
A11: LIPIGAS | B11: Dividendos | C11: Trii | D11: 9 | E11: 4433 | F11: 8700 | G11: 39897 | H11: 78300 | I11: 5976 | J11: =IF(G11=0,"",(H11+I11-G11)/G11) | L11: =H11/$H$19
A12: AGUAS-A (Aguas Andinas) | B12: Dividendos | C12: Zesty | D12: 56 | E12: 336.47 | F12: 333.5714 | G12: 18842.32 | H12: 18680 | I12: 0 | J12: =IF(G12=0,"",(H12+I12-G12)/G12) | L12: =H12/$H$19
A13: PEHUENCHE | B13: Dividendos | C13: Zesty | D13: 7 | E13: 2644.6 | F13: 2559.7143 | G13: 18512.2 | H13: 17918 | I13: 0 | J13: =IF(G13=0,"",(H13+I13-G13)/G13) | L13: =H13/$H$19
A14: QUIÑENCO | B14: Dividendos | C14: Zesty | D14: 3 | E14: 3865.3 | F14: 3871 | G14: 11595.9 | H14: 11613 | I14: 0 | J14: =IF(G14=0,"",(H14+I14-G14)/G14) | L14: =H14/$H$19
A15: VWO (Emerging Markets ETF) | B15: Emergentes | C15: XTB | D15: 1.962 | G15: 97944.07 | H15: 105779.6 | I15: 0 | J15: =IF(G15=0,"",(H15+I15-G15)/G15) | L15: =H15/$H$19
A16: MSFT (Microsoft) | B16: USA | C16: XTB | D16: 0.149 | G16: 50995.15 | H16: 51102.24 | I16: 0 | J16: =IF(G16=0,"",(H16+I16-G16)/G16) | L16: =H16/$H$19
A17: AAPL (Apple) | B17: USA | C17: XTB | D17: 0.0045 | G17: 1032.2 | H17: 1176.6 | I17: 0 | J17: =IF(G17=0,"",(H17+I17-G17)/G17) | L17: =H17/$H$19
A18: BTC (Bitcoin) | B18: Crypto | C18: Binance | D18: 0.00327023 | G18: 222070.94 | H18: 181321 | I18: 0 | J18: =IF(G18=0,"",(H18+I18-G18)/G18) | L18: =H18/$H$19
A19: TOTAL | G19: =SUM(G4:G18) | H19: =SUM(H4:H18) | I19: =SUM(I4:I18) | L19: =SUM(L4:L18)
A21: Nota: para VWO, MSFT, AAPL y BTC, ingresa el Valor Mercado (col. H) directo en CLP tal como lo muestra XTB/Binance (ya viene convertido).
A22: Para CHILE, completa Precio Compra (col. E) con tu costo promedio real cuando lo tengas a mano (quedó vacío porque hubo compras en distintos precios).

Sheet Tesis - Checklist
A1: TESIS — CHECKLIST RÁPIDO (completar y revisar cada 6 meses)
A3: Empresa | B3: Categoría | C3: Tipo de Moat | D3: Payout ratio sobre FCF | E3: Yield actual vs. histórico propio | F3: Condición de SALIDA (escribir ANTES de comprar más) | G3: Convicción (1-5) | H3: ¿La compraría hoy? (S/N) | I3: Última revisión | J3: Notas
A4: CHILE (Banco de Chile) | C4: Regulatorio + escala (banca) | E4: 5,99% actual vs. ~5,5-7% histórico propio (payout ~80% sostenido) → EN LÍNEA, sin señal de yield trap. | I4: 26/06/2026 | J4: Precio ref. ~$165-169. Dividendo creciente 10 años seguidos.
A5: ZOFRI | C5: Concesión/Ley única — riesgo regulatorio binario | E5: ~7,2-9,5% actual vs. ~9,7-10,1% en 2023-2024 → algo MÁS CARA que su propio promedio reciente; hoy no es el mejor punto de entrada. | I5: 26/06/2026 | J5: Dividendo históricamente volátil (riesgo concesión). Payout sobre FCF/caja ~107% → vigilar sostenibilidad.
A6: LIPIGAS | C6: Oligopolio regional | E6: ~6,5% actual (calc.: ~$535/acción anual ÷ $8.158 precio) vs. dividendo cayendo ~-4%/año últimos 5 años → yield 'sostenido' pero porque el dividendo BAJA, no por crecimiento. Señal de precaución. | I6: 26/06/2026 | J6: Vigilar FCF: 5 años seguidos de caída en dividendo es bandera amarilla para la tesis.
A7: AGUAS-A (Aguas Andinas) | C7: Concesión monopólica regulada | E7: ~4,1-5,0% actual vs. dividendo cayendo ~-2%/año últimos 3 años → yield en la parte BAJA de su propio rango; no es la más atractiva esta semana. | I7: 26/06/2026 | J7: Payout ~70%, ROE ~10,7%. Concesión estable, pero dividendo no crece.
A8: PEHUENCHE | C8: Débil — generador pequeño, riesgo hidrológico estructural | E8: ~10,0-10,6% actual vs. 9,6% (2023) y 10,6% (2024) → EN LÍNEA con su historial reciente, en la parte alta y consistente. | I8: 26/06/2026 | J8: Payout 100% en 2024 (alto, pero generador regulado con flujos estables). De los 6, la más atractiva por yield esta semana.
A9: QUIÑENCO | C9: Holding — moat heredado de sus controladas (revisar duplicidad con CHILE) | E9: Yield 'regular' recurrente ~2,8% — la lectura de 8-9% que muestran algunos screeners incluye un dividendo EXTRAORDINARIO reciente (~100% utilidad del ejercicio), no recurrente. | I9: 26/06/2026 | J9: ⚠ No comprar guiado por el yield 'titular' actual: es no recurrente. Yield sostenible real ~2,8%, el más bajo de los 6.
A10: CFINRENTAS (Rentas Inmob.)
A11: CFMITNIPSA (ETF IPSA)
A12: CFISPETF (ETF S&P500)
A13: CFINASDAQ (ETF Nasdaq)
A14: VWO (Emergentes)
A15: MSFT
A16: AAPL
A17: BTC (Bitcoin)

Sheet Tesis - Detalle
A1: TESIS DETALLADA — usar solo para posiciones grandes o de alta convicción
A2: Duplica este bloque (copiar filas 4-20) por cada empresa que quieras analizar en profundidad.
A4: EMPRESA / TICKER
A5: 1. Negocio: ¿qué vende y a quién? ¿Necesidad o discrecional?
A6: 2. Moat — mecanismo específico (regulación / escala / marca / costo de cambio / red)
A7: 3. Tipo de moat: ¿económico o regulatorio/concesión? (un moat regulatorio es riesgo binario, no gradual)
A8: 4. Ingresos y FCF — tendencia últimos 5 años
A9: 5. Payout ratio sobre FCF (no sobre utilidad contable) — ¿sostenible?
A10: 6. Deuda / apalancamiento — ¿compromete el dividendo en un ciclo bajo?
A11: 7. Valuación — yield actual vs. promedio histórico propio y vs. pares del sector
A12: 8. Catalizadores — qué la haría crecer
A13: 9. Riesgos específicos — qué la rompe (regulatorio, clima, competencia, tecnología)
... A21: EJEMPLO YA COMPLETADO (Banco de Chile) — bórralo o úsalo de referencia
A22: EMPRESA / TICKER | B22: CHILE — Banco de Chile
A23: 1. Negocio | B23: Banca universal en Chile. Servicio de necesidad (cuentas, crédito, pagos).
A24: 2. Moat | B24: Escala, marca, base de depositantes, licencia bancaria regulada.
A25: 3. Tipo de moat | B25: Económico + regulatorio combinado. Más robusto que un moat 100% regulatorio.
A26: 4. Ingresos/FCF | B26: Revisar últimos 5 años en memoria anual / informes CMF.
A27: 5. Payout/FCF | B27: Revisar dividendo pagado vs. utilidad distribuible reportada.
A28: 6. Deuda | B28: Bancos operan apalancados por naturaleza — foco en calidad de cartera, no en deuda tradicional.
A29: 7. Valuación | B29: Comparar yield actual vs. promedio 5 años propio y vs. Santander-Chile/BCI.
A30: 8. Catalizadores | B30: Crecimiento de colocaciones, control de costos, ciclo de tasas favorable.
A31: 9. Riesgos | B31: Riesgo sistémico bancario, regulación CMF, mora en ciclo de tasas altas.
A32: 10. Condición de salida | B32: Vendo si: deterioro sostenido de cartera (mora >X% por 2 trimestres) o cambio regulatorio que limite dividendo.
A33: 11. Test Buffett | B33: [completar]
... A36: Próxima revisión | B36: [completar]

Sheet Parámetros Proyección
A1: PARÁMETROS DE PROYECCIÓN — edita los valores amarillos y todo se recalcula
A3: Aporte mensual inicial (CLP): | B3: 150000
A4: Crecimiento anual del aporte: | B4: 0.05
A5: Tope máximo Cripto (% portafolio): | B5: 0.15
A6: Fecha inicio proyección: | B6: =DATE(2026,7,1)
A7: Meta ingreso pasivo mensual (hoy): | B7: 2000000
A9: SUPUESTOS DE RETORNO POR CATEGORÍA (anuales, edítalos libremente)
A10: Categoría | B10: Yield anual | C10: Apreciación anual | D10: Retorno total anual | E10: Retorno mensual (apreciación) | F10: Retorno mensual (yield) | G10: Peso objetivo (aportes nuevos)
A11: Dividendos | B11: 0.065 | C11: 0.035 | D11: =(1+B11)*(1+C11)-1 | E11: =(1+C11)^(1/12)-1 | F11: =(1+B11)^(1/12)-1 | G11: 0.7
A12: USA | B12: 0.013 | C12: 0.085 | D12: =(1+B12)*(1+C12)-1 | E12: =(1+C12)^(1/12)-1 | F12: =(1+B12)^(1/12)-1 | G12: 0.075
A13: Emergentes | B13: 0.028 | C13: 0.06 | D13: =(1+B13)*(1+C13)-1 | E13: =(1+C13)^(1/12)-1 | F13: =(1+B13)^(1/12)-1 | G13: 0.075
A14: Internacional | B14: 0.025 | C14: 0.065 | D14: =(1+B14)*(1+C14)-1 | E14: =(1+C14)^(1/12)-1 | F14: =(1+B14)^(1/12)-1 | G14: 0.075
A15: Crypto | B15: 0 | C15: 0.15 | D15: =(1+B15)*(1+C15)-1 | E15: =(1+C15)^(1/12)-1 | F15: =(1+B15)^(1/12)-1 | G15: 0.075
A16: Suma pesos: | G16: =SUM(G11:G15)

Sheet Proyección Mensual
A1: PROYECCIÓN MENSUAL (motor de cálculo — no editar manualmente, se alimenta de 'Parámetros Proyección' y 'Cartera Detalle')
A3: Mes | B3: Fecha | C3: Año | D3: Aporte base | E3: Dividendos Saldo Ini | F3: Dividendos Post Apr. | G3: Dividendos Div. mes | H3: Dividendos Post Crec. | I3: Dividendos Aporte | J3: Dividendos Saldo Fin | K3: USA Saldo Ini | L3: USA Post Apr. | M3: USA Div. mes | N3: USA Post Crec. | O3: USA Aporte | P3: USA Saldo Fin | Q3: Emergentes Saldo Ini | R3: Emergentes Post Apr. | S3: Emergentes Div. mes | T3: Emergentes Post Crec. | U3: Emergentes Aporte | V3: Emergentes Saldo Fin | W3: Internacional Saldo Ini | X3: Internacional Post Apr. | Y3: Internacional Div. mes | Z3: Internacional Post Crec. | AA3: Internacional Aporte | AB3: Internacional Saldo Fin | AC3: Crypto Saldo Ini | AD3: Crypto Post Apr. | AE3: Crypto Div. mes | AF3: Crypto Post Crec. | AG3: Crypto Aporte | AH3: Crypto Saldo Fin | AI3: Total Post Crec. | AJ3: % Cripto (post crec.) | AK3: Cripto ¿sobre tope? | AL3: Dividendos del mes (tot) | AM3: Aportes acumulados | AN3: Dividendos acumulados | AO3: TOTAL PORTAFOLIO
A4: 1 | B4: ='Parámetros Proyección'!$B$6 | C4: =YEAR(B4) | D4: ='Parámetros Proyección'!$B$3*(1+'Parámetros Proyección'!$B$4)^(C4-YEAR('Parámetros Proyección'!$B$6)) | E4: =SUMIF('Cartera Detalle'!$B$4:$B$18,"Dividendos",'Cartera Detalle'!$H$4:$H$18) | F4: =E4*(1+'Parámetros Proyección'!$E$11) | G4: =F4*'Parámetros Proyección'!$F$11 | H4: =F4+G4 | I4: =IF((H4/AI4>'Parámetros Proyección'!$G$11),0,D4*'Parámetros Proyección'!$G$11/(IF((H4/AI4>'Parámetros Proyección'!$G$11),0,'Parámetros Proyección'!$G$11)+IF((N4/AI4>'Parámetros Proyección'!$G$12),0,'Parámetros Proyección'!$G$12)+IF((T4/AI4>'Parámetros Proyección'!$G$13),0,'Parámetros Proyección'!$G$13)+IF((Z4/AI4>'Parámetros Proyección'!$G$14),0,'Parámetros Proyección'!$G$14)+IF((AF4/AI4>'Parámetros Proyección'!$G$15),0,'Parámetros Proyección'!$G$15))) | J4: =H4+I4 | K4: =SUMIF('Cartera Detalle'!$B$4:$B$18,"USA",'Cartera Detalle'!$H$4:$H$18) | L4: =K4*(1+'Parámetros Proyección'!$E$12) | M4: =L4*'Parámetros Proyección'!$F$12 | N4: =L4+M4 | O4: =IF((N4/AI4>'Parámetros Proyección'!$G$12),0,D4*'Parámetros Proyección'!$G$12/(IF((H4/AI4>'Parámetros Proyección'!$G$11),0,'Parámetros Proyección'!$G$11)+IF((N4/AI4>'Parámetros Proyección'!$G$12),0,'Parámetros Proyección'!$G$12)+IF((T4/AI4>'Parámetros Proyección'!$G$13),0,'Parámetros Proyección'!$G$13)+IF((Z4/AI4>'Parámetros Proyección'!$G$14),0,'Parámetros Proyección'!$G$14)+IF((AF4/AI4>'Parámetros Proyección'!$G$15),0,'Parámetros Proyección'!$G$15))) | P4: =N4+O4 | Q4: =SUMIF('Cartera Detalle'!$B$4:$B$18,"Emergentes",'Cartera Detalle'!$H$4:$H$18) | R4: =Q4*(1+'Parámetros Proyección'!$E$13) | S4: =R4*'Parámetros Proyección'!$F$13 | T4: =R4+S4 | U4: =IF((T4/AI4>'Parámetros Proyección'!$G$13),0,D4*'Parámetros Proyección'!$G$13/(IF((H4/AI4>'Parámetros Proyección'!$G$11),0,'Parámetros Proyección'!$G$11)+IF((N4/AI4>'Parámetros Proyección'!$G$12),0,'Parámetros Proyección'!$G$12)+IF((T4/AI4>'Parámetros Proyección'!$G$13),0,'Parámetros Proyección'!$G$13)+IF((Z4/AI4>'Parámetros Proyección'!$G$14),0,'Parámetros Proyección'!$G$14)+IF((AF4/AI4>'Parámetros Proyección'!$G$15),0,'Parámetros Proyección'!$G$15))) | V4: =T4+U4 | W4: =SUMIF('Cartera Detalle'!$B$4:$B$18,"Internacional",'Cartera Detalle'!$H$4:$H$18) | X4: =W4*(1+'Parámetros Proyección'!$E$14) | Y4: =X4*'Parámetros Proyección'!$F$14 | Z4: =X4+Y4 | AA4: =IF((Z4/AI4>'Parámetros Proyección'!$G$14),0,D4*'Parámetros Proyección'!$G$14/(IF((H4/AI4>'Parámetros Proyección'!$G$11),0,'Parámetros Proyección'!$G$11)+IF((N4/AI4>'Parámetros Proyección'!$G$12),0,'Parámetros Proyección'!$G$12)+IF((T4/AI4>'Parámetros Proyección'!$G$13),0,'Parámetros Proyección'!$G$13)+IF((Z4/AI4>'Parámetros Proyección'!$G$14),0,'Parámetros Proyección'!$G$14)+IF((AF4/AI4>'Parámetros Proyección'!$G$15),0,'Parámetros Proyección'!$G$15))) | AB4: =Z4+AA4 | AC4: =SUMIF('Cartera Detalle'!$B$4:$B$18,"Crypto",'Cartera Detalle'!$H$4:$H$18) | AD4: =AC4*(1+'Parámetros Proyección'!$E$15) | AE4: =AD4*'Parámetros Proyección'!$F$15 | AF4: =AD4+AE4 | AG4: =IF((AF4/AI4>'Parámetros Proyección'!$G$15),0,D4*'Parámetros Proyección'!$G$15/(IF((H4/AI4>'Parámetros Proyección'!$G$11),0,'Parámetros Proyección'!$G$11)+IF((N4/AI4>'Parámetros Proyección'!$G$12),0,'Parámetros Proyección'!$G$12)+IF((T4/AI4>'Parámetros Proyección'!$G$13),0,'Parámetros Proyección'!$G$13)+IF((Z4/AI4>'Parámetros Proyección'!$G$14),0,'Parámetros Proyección'!$G$14)+IF((AF4/AI4>'Parámetros Proyección'!$G$15),0,'Parámetros Proyección'!$G$15))) | AH4: =AF4+AG4 | AI4: =H4+N4+T4+Z4+AF4 | AJ4: =AF4/AI4 | AK4: =IF(AJ4>'Parámetros Proyección'!$B$5,1,0) | AL4: =G4+M4+S4+Y4+AE4 | AM4: =D4 | AN4: =AL4 | AO4: =J4+P4+V4+AB4+AH4
A5: 2 | B5: =EDATE(B4,1) | C5: =YEAR(B5) | D5: ='Parámetros Proyección'!$B$3*(1+'Parámetros Proyección'!$B$4)^(C5-YEAR('Parámetros Proyección'!$B$6)) | E5: =J4 | F5: =E5*(1+'Parámetros Proyección'!$E$11) | G5: =F5*'Parámetros Proyección'!$F$11 | H5: =F5+G5 | I5: =IF((H5/AI5>'Parámetros Proyección'!$G$11),0,D5*'Parámetros Proyección'!$G$11/(IF((H5/AI5>'Parámetros Proyección'!$G$11),0,'Parámetros Proyección'!$G$11)+IF((N5/AI5>'Parámetros Proyección'!$G$12),0,'Parámetros Proyección'!$G$12)+IF((T5/AI5>'Parámetros Proyección'!$G$13),0,'Parámetros Proyección'!$G$13)+IF((Z5/AI5>'Parámetros Proyección'!$G$14),0,'Parámetros Proyección'!$G$14)+IF((AF5/AI5>'Parámetros Proyección'!$G$15),0,'Parámetros Proyección'!$G$15))) | J5: =H5+I5 | K5: =P4 | L5: =K5*(1+'Parámetros Proyección'!$E$12) | M5: =L5*'Parámetros Proyección'!$F$12 | N5: =L5+M5 | O5: =IF((N5/AI5>'Parámetros Proyección'!$G$12),0,D5*'Parámetros Proyección'!$G$12/(IF((H5/AI5>'Parámetros Proyección'!$G$11),0,'Parámetros Proyección'!$G$11)+IF((N5/AI5>'Parámetros Proyección'!$G$12),0,'Parámetros Proyección'!$G$12)+IF((T5/AI5>'Parámetros Proyección'!$G$13),0,'Parámetros Proyección'!$G$13)+IF((Z5/AI5>'Parámetros Proyección'!$G$14),0,'Parámetros Proyección'!$G$14)+IF((AF5/AI5>'Parámetros Proyección'!$G$15),0,'Parámetros Proyección'!$G$15))) | P5: =N5+O5 | Q5: =V4 | R5: =Q5*(1+'Parámetros Proyección'!$E$13) | S5: =R5*'Parámetros Proyección'!$F$13 | T5: =R5+S5 | U5: =IF((T5/AI5>'Parámetros Proyección'!$G$13),0,D5*'Parámetros Proyección'!$G$13/(IF((H5/AI5>'Parámetros Proyección'!$G$11),0,'Parámetros Proyección'!$G$11)+IF((N5/AI5>'Parámetros Proyección'!$G$12),0,'Parámetros Proyección'!$G$12)+IF((T5/AI5>'Parámetros Proyección'!$G$13),0,'Parámetros Proyección'!$G$13)+IF((Z5/AI5>'Parámetros Proyección'!$G$14),0,'Parámetros Proyección'!$G$14)+IF((AF5/AI5>'Parámetros Proyección'!$G$15),0,'Parámetros Proyección'!$G$15))) | V5: =T5+U5 | W5: =AB4 | X5: =W5*(1+'Parámetros Proyección'!$E$14) | Y5: =X5*'Parámetros Proyección'!$F$14 | Z5: =X5+Y5 | AA5: =IF((Z5/AI5>'Parámetros Proyección'!$G$14),0,D5*'Parámetros Proyección'!$G$14/(IF((H5/AI5>'Parámetros Proyección'!$G$11),0,'Parámetros Proyección'!$G$11)+IF((N5/AI5>'Parámetros Proyección'!$G$12),0,'Parámetros Proyección'!$G$12)+IF((T5/AI5>'Parámetros Proyección'!$G$13),0,'Parámetros Proyección'!$G$13)+IF((Z5/AI5>'Parámetros Proyección'!$G$14),0,'Parámetros Proyección'!$G$14)+IF((AF5/AI5>'Parámetros Proyección'!$G$15),0,'Parámetros Proyección'!$G$15))) | AB5: =Z5+AA5 | AC5: =AH4 | AD5: =AC5*(1+'Parámetros Proyección'!$E$15) | AE5: =AD5*'Parámetros Proyección'!$F$15 | AF5: =AD5+AE5 | AG5: =IF((AF5/AI5>'Parámetros Proyección'!$G$15),0,D5*'Parámetros Proyección'!$G$15/(IF((H5/AI5>'Parámetros Proyección'!$G$11),0,'Parámetros Proyección'!$G$11)+IF((N5/AI5>'Parámetros Proyección'!$G$12),0,'Parámetros Proyección'!$G$12)+IF((T5/AI5>'Parámetros Proyección'!$G$13),0,'Parámetros Proyección'!$G$13)+IF((Z5/AI5>'Parámetros Proyección'!$G$14),0,'Parámetros Proyección'!$G$14)+IF((AF5/AI5>'Parámetros Proyección'!$G$15),0,'Parámetros Proyección'!$G$15))) | AH5: =AF5+AG5 | AI5: =H5+N5+T5+Z5+AF5 | AJ5: =AF5/AI5 | AK5: =IF(AJ5>'Parámetros Proyección'!$B$5,1,0) | AL5: =G5+M5+S5+Y5+AE5 | AM5: =AM4+D5 | AN5: =AN4+AL5 | AO5: =J5+P5+V5+AB5+AH5
A6: 3 | B6: =EDATE(B5,1) | C6: =YEAR(B6) | D6: ='Parámetros Proyección'!$B$3*(1+'Parámetros Proyección'!$B$4)^(C6-YEAR('Parámetros Proyección'!$B$6)) | E6: =J5 | F6: =E6*(1+'Parámetros Proyección'!$E$11) | G6: =F6*'Parámetros Proyección'!$F$11 | H6: =F6+G6 | I6: =IF((H6/AI6>'Parámetros Proyección'!$G$11),0,D6*'Parámetros Proyección'!$G$11/(IF((H6/AI6>'Parámetros Proyección'!$G$11),0,'Parámetros Proyección'!$G$11)+IF((N6/AI6>'Parámetros Proyección'!$G$12),0,'Parámetros Proyección'!$G$12)+IF((T6/AI6>'Parámetros Proyección'!$G$13),0,'Parámetros Proyección'!$G$13)+IF((Z6/AI6>'Parámetros Proyección'!$G$14),0,'Parámetros Proyección'!$G$14)+IF((AF6/AI6>'Parámetros Proyección'!$G$15),0,'Parámetros Proyección'!$G$15))) | J6: =H6+I6 | K6: =P5 | L6: =K6*(1+'Parámetros Proyección'!$E$12) | M6: =L6*'Parámetros Proyección'!$F$12 | N6: =L6+M6 | O6: =IF((N6/AI6>'Parámetros Proyección'!$G$12),0,D6*'Parámetros Proyección'!$G$12/(IF((H6/AI6>'Parámetros Proyección'!$G$11),0,'Parámetros Proyección'!$G$11)+IF((N6/AI6>'Parámetros Proyección'!$G$12),0,'Parámetros Proyección'!$G$12)+IF((T6/AI6>'Parámetros Proyección'!$G$13),0,'Parámetros Proyección'!$G$13)+IF((Z6/AI6>'Parámetros Proyección'!$G$14),0,'Parámetros Proyección'!$G$14)+IF((AF6/AI6>'Parámetros Proyección'!$G$15),0,'Parámetros Proyección'!$G$15))) | P6: =N6+O6 | Q6: =V5 | R6: =Q6*(1+'Parámetros Proyección'!$E$13) | S6: =R6*'Parámetros Proyección'!$F$13 | T6: =R6+S6 | U6: =IF((T6/AI6>'Parámetros Proyección'!$G$13),0,D6*'Parámetros Proyección'!$G$13/(IF((H6/AI6>'Parámetros Proyección'!$G$11),0,'Parámetros Proyección'!$G$11)+IF((N6/AI6>'Parámetros Proyección'!$G$12),0,'Parámetros Proyección'!$G$12)+IF((T6/AI6>'Parámetros Proyección'!$G$13),0,'Parámetros Proyección'!$G$13)+IF((Z6/AI6>'Parámetros Proyección'!$G$14),0,'Parámetros Proyección'!$G$14)+IF((AF6/AI6>'Parámetros Proyección'!$G$15),0,'Parámetros Proyección'!$G$15))) | V6: =T6+U6 | W6: =AB5 | X6: =W6*(1+'Parámetros Proyección'!$E$14) | Y6: =X6*'Parámetros Proyección'!$F$14 | Z6: =X6+Y6 | AA6: =IF((Z6/AI6>'Parámetros Proyección'!$G$14),0,D6*'Parámetros Proyección'!$G$14/(IF((H6/AI6>'Parámetros Proyección'!$G$11),0,'Parámetros Proyección'!$G$11)+IF((N6/AI6>'Parámetros Proyección'!$G$12),0,'Parámetros Proyección'!$G$12)+IF((T6/AI6>'Parámetros Proyección'!$G$13),0,'Parámetros Proyección'!$G$13)+IF((Z6/AI6>'Parámetros Proyección'!$G$14),0,'Parámetros Proyección'!$G$14)+IF((AF6/AI6>'Parámetros Proyección'!$G$15),0,'Parámetros Proyección'!$G$15))) | AB6: =Z6+AA6 | AC6: =AH5 | AD6: =AC6*(1+'Parámetros Proyección'!$E$15) | AE6: =AD6*'Parámetros Proyección'!$F$15 | AF6: =AD6+AE6 | AG6: =IF((AF6/AI6>'Parámetros Proyección'!$G$15),0,D6*'Parámetros Proyección'!$G$15/(IF((H6/AI6>'Parámetros Proyección'!$G$11),0,'Parámetros Proyección'!$G$11)+IF((N6/AI6>'Parámetros Proyección'!$G$12),0,'Parámetros Proyección'!$G$12)+IF((T6/AI6>'Parámetros Proyección'!$G$13),0,'Parámetros Proyección'!$G$13)+IF((Z6/AI6>'Parámetros Proyección'!$G$14),0,'Parámetros Proyección'!$G$14)+IF((AF6/AI6>'Parámetros Proyección'!$G$15),0,'Parámetros Proyección'!$G$15))) | AH6: =AF6+AG6 | AI6: =H6+N6+T6+Z6+AF6 | AJ6: =AF6/AI6 | AK6: =IF(AJ6>'Parámetros Proyección'!$B$5,1,0) | AL6: =G6+M6+S6+Y6+AE6 | AM6: =AM5+D6 | AN6: =AN5+AL6 | AO6: =J6+P6+V6+AB6+AH6
A7: 4 | B7: =EDATE(B6,1) | C7: =YEAR(B7) | D7: ='Parámetros Proyección'!$B$3*(1+'Parámetros Proyección'!$B$4)^(C7-YEAR('Parámetros Proyección'!$B$6)) | E7: =J6 | F7: =E7*(1+'Parámetros Proyección'!$E$11) | G7: =F7*'Parámetros Proyección'!$F$11 | H7: =F7+G7 | I7: =IF((H7/AI7>'Parámetros Proyección'!$G$11),0,D7*'Parámetros Proyección'!$G$11/(IF((H7/AI7>'Parámetros Proyección'!$G$11),0,'Parámetros Proyección'!$G$11)+IF((N7/AI7>'Parámetros Proyección'!$G$12),0,'Parámetros Proyección'!$G$12)+IF((T7/AI7>'Parámetros Proyección'!$G$13),0,'Parámetros Proyección'!$G$13)+IF((Z7/AI7>'Parámetros Proyección'!$G$14),0,'Parámetros Proyección'!$G$14)+IF((AF7/AI7>'Parámetros Proyección'!$G$15),0,'Parámetros Proyección'!$G$15))) | J7: =H7+I7 | K7: =P6 | L7: =K7*(1+'Parámetros Proyección'!$E$12) | M7: =L7*'Parámetros Proyección'!$F$12 | N7: =L7+M7 | O7: =IF((N7/AI7>'Parámetros Proyección'!$G$12),0,D7*'Parámetros Proyección'!$G$12/(IF((H7/AI7>'Parámetros Proyección'!$G$11),0,'Parámetros Proyección'!$G$11)+IF((N7/AI7>'Parámetros Proyección'!$G$12),0,'Parámetros Proyección'!$G$12)+IF((T7/AI7>'Parámetros Proyección'!$G$13),0,'Parámetros Proyección'!$G$13)+IF((Z7/AI7>'Parámetros Proyección'!$G$14),0,'Parámetros Proyección'!$G$14)+IF((AF7/AI7>'Parámetros Proyección'!$G$15),0,'Parámetros Proyección'!$G$15))) | P7: =N7+O7 | Q7: =V6 | R7: =Q7*(1+'Parámetros Proyección'!$E$13) | S7: =R7*'Parámetros Proyección'!$F$13 | T7: =R7+S7 | U7: =IF((T7/AI7>'Parámetros Proyección'!$G$13),0,D7*'Parámetros Proyección'!$G$13/(IF((H7/AI7>'Parámetros Proyección'!$G$11),0,'Parámetros Proyección'!$G$11)+IF((N7/AI7>'Parámetros Proyección'!$G$12),0,'Parámetros Proyección'!$G$12)+IF((T7/AI7>'Parámetros Proyección'!$G$13),0,'Parámetros Proyección'!$G$13)+IF((Z7/AI7>'Parámetros Proyección'!$G$14),0,'Parámetros Proyección'!$G$14)+IF((AF7/AI7>'Parámetros Proyección'!$G$15),0,'Parámetros Proyección'!$G$15))) | V7: =T7+U7 | W7: =AB6 | X7: =W7*(1+'Parámetros Proyección'!$E$14) | Y7: =X7*'Parámetros Proyección'!$F$14 | Z7: =X7+Y7 | AA7: =IF((Z7/AI7>'Parámetros Proyección'!$G$14),0,D7*'Parámetros Proyección'!$G$14/(IF((H7/AI7>'Parámetros Proyección'!$G$11),0,'Parámetros Proyección'!$G$11)+IF((N7/AI7>'Parámetros Proyección'!$G$12),0,'Parámetros Proyección'!$G$12)+IF((T7/AI7>'Parámetros Proyección'!$G$13),0,'Parámetros Proyección'!$G$13)+IF((Z7/AI7>'Parámetros Proyección'!$G$14),0,'Parámetros Proyección'!$G$14)+IF((AF7/AI7>'Parámetros Proyección'!$G$15),0,'Parámetros Proyección'!$G$15))) | AB7: =Z7+AA7 | AC7: =AH6 | AD7: =AC7*(1+'Parámetros Proyección'!$E$15) | AE7: =AD7*'Parámetros Proyección'!$F$15 | AF7: =AD7+AE7 | AG7: =IF((AF7/AI7>'Parámetros Proyección'!$G$15),0,D7*'Parámetros Proyección'!$G$15/(IF((H7/AI7>'Parámetros Proyección'!$G$11),0,'Parámetros Proyección'!$G$11)+IF((N7/AI7>'Parámetros Proyección'!$G$12),0,'Parámetros Proyección'!$G$12)+IF((T7/AI7>'Parámetros Proyección'!$G$13),0,'Parámetros Proyección'!$G$13)+IF((Z7/AI7>'Parámetros Proyección'!$G$14),0,'Parámetros Proyección'!$G$14)+IF((AF7/AI7>'Parámetros Proyección'!$G$15),0,'Parámetros Proyección'!$G$15))) | AH7: =AF7+AG7 | AI7: =H7+N7+T7+Z7+AF7 | AJ7: =AF7/AI7 | AK7: =IF(AJ7>'Parámetros Proyección'!$B$5,1,0) | AL7: =G7+M7+S7+Y7+AE7 | AM7: =AM6+D7 | AN7: =AN6+AL7 | AO7: =J7+P7+V7+AB7+AH7
A8: 5 | B8: =EDATE(B7,1) | C8: =YEAR(B8) | D8: ='Parámetros Proyección'!$B$3*(1+'Parámetros Proyección'!$B$4)^(C8-YEAR('Parámetros Proyección'!$B$6)) | E8: =J7 | F8: =E8*(1+'Parámetros Proyección'!$E$11) | G8: =F8*'Parámetros Proyección'!$F$11 | H8: =F8+G8 | I8: =IF((H8/AI8>'Parámetros Proyección'!$G$11),0,D8*'Parámetros Proyección'!$G$11/(IF((H8/AI8>'Parámetros Proyección'!$G$11),0,'Parámetros Proyección'!$G$11)+IF((N8/AI8>'Parámetros Proyección'!$G$12),0,'Parámetros Proyección'!$G$12)+IF((T8/AI8>'Parámetros Proyección'!$G$13),0,'Parámetros Proyección'!$G$13)+IF((Z8/AI8>'Parámetros Proyección'!$G$14),0,'Parámetros Proyección'!$G$14)+IF((AF8/AI8>'Parámetros Proyección'!$G$15),0,'Parámetros Proyección'!$G$15))) | J8: =H8+I8 | K8: =P7 | L8: =K8*(1+'Parámetros Proyección'!$E$12) | M8: =L8*'Parámetros Proyección'!$F$12 | N8: =L8+M8 | O8: =IF((N8/AI8>'Parámetros Proyección'!$G$12),0,D8*'Parámetros Proyección'!$G$12/(IF((H8/AI8>'Parámetros Proyección'!$G$11),0,'Parámetros Proyección'!$G$11)+IF((N8/AI8>'Parámetros Proyección'!$G$12),0,'Parámetros Proyección'!$G$12)+IF((T8/AI8>'Parámetros Proyección'!$G$13),0,'Parámetros Proyección'!$G$13)+IF((Z8/AI8>'Parámetros Proyección'!$G$14),0,'Parámetros Proyección'!$G$14)+IF((AF8/AI8>'Parámetros Proyección'!$G$15),0,'Parámetros Proyección'!$G$15))) | P8: =N8+O8 | Q8: =V7 | R8: =Q8*(1+'Parámetros Proyección'!$E$13) | S8: =R8*'Parámetros Proyección'!$F$13 | T8: =R8+S8 | U8: =IF((T8/AI8>'Parámetros Proyección'!$G$13),0,D8*'Parámetros Proyección'!$G$13/(IF((H8/AI8>'Parámetros Proyección'!$G$11),0,'Parámetros Proyección'!$G$11)+IF((N8/AI8>'Parámetros Proyección'!$G$12),0,'Parámetros Proyección'!$G$12)+IF((T8/AI8>'Parámetros Proyección'!$G$13),0,'Parámetros Proyección'!$G$13)+IF((Z8/AI8>'Parámetros Proyección'!$G$14),0,'Parámetros Proyección'!$G$14)+IF((AF8/AI8>'Parámetros Proyección'!$G$15),0,'Parámetros Proyección'!$G$15))) | V8: =T8+U8 | W8: =AB7 | X8: =W8*(1+'Parámetros Proyección'!$E$14) | Y8: =X8*'Parámetros Proyección'!$F$14 | Z8: =X8+Y8 | AA8: =IF((Z8/AI8>'Parámetros Proyección'!$G$14),0,D8*'Parámetros Proyección'!$G$14/(IF((H8/AI8>'Parámetros Proyección'!$G$11),0,'Parámetros Proyección'!$G$11)+IF((N8/AI8>'Parámetros Proyección'!$G$12),0,'Parámetros Proyección'!$G$12)+IF((T8/AI8>'Parámetros Proyección'!$G$13),0,'Parámetros Proyección'!$G$13)+IF((Z8/AI8>'Parámetros Proyección'!$G$14),0,'Parámetros Proyección'!$G$14)+IF((AF8/AI8>'Parámetros Proyección'!$G$15),0,'Parámetros Proyección'!$G$15))) | AB8: =Z8+AA8 | AC8: =AH7 | AD8: =AC8*(1+'Parámetros Proyección'!$E$15) | AE8: =AD8*'Parámetros Proyección'!$F$15 | AF8: =AD8+AE8 | AG8: =IF((AF8/AI8>'Parámetros Proyección'!$G$15),0,D8*'Parámetros Proyección'!$G$15/(IF((H8/AI8>'Parámetros Proyección'!$G$11),0,'Parámetros Proyección'!$G$11)+IF((N8/AI8>'Parámetros Proyección'!$G$12),0,'Parámetros Proyección'!$G$12)+IF((T8/AI8>'Parámetros Proyección'!$G$13),0,'Parámetros Proyección'!$G$13)+IF((Z8/AI8>'Parámetros Proyección'!$G$14),0,'Parámetros Proyección'!$G$14)+IF((AF8/AI8>'Parámetros Proyección'!$G$15),0,'Parámetros Proyección'!$G$15))) | AH8: =AF8+AG8 | AI8: =H8+N8+T8+Z8+AF8 | AJ8: =AF8/AI8 | AK8: =IF(AJ8>'Parámetros Proyección'!$B$5,1,0) | AL8: =G8+M8+S8+Y8+AE8 | AM8: =AM7+D8 | AN8: =AN7+AL8 | AO8: =J8+P8+V8+AB8+AH8
A9: 6 | B9: =EDATE(B8,1) | C9: =YEAR(B9) | D9: ='Parámetros Proyección'!$B$3*(1+'Parámetros Proyección'!$B$4)^(C9-YEAR('Parámetros Proyección'!$B$6)) | E9: =J8 | F9: =E9*(1+'Parámetros Proyección'!$E$11) | G9: =F9*'Parámetros Proyección'!$F$11 | H9: =F9+G9 | I9: =IF((H9/AI9>'Parámetros Proyección'!$G$11),0,D9*'Parámetros Proyección'!$G$11/(IF((H9/AI9>'Parámetros Proyección'!$G$11),0,'Parámetros Proyección'!$G$11)+IF((N9/AI9>'Parámetros Proyección'!$G$12),0,'Parámetros Proyección'!$G$12)+IF((T9/AI9>'Parámetros Proyección'!$G$13),0,'Parámetros Proyección'!$G$13)+IF((Z9/AI9>'Parámetros Proyección'!$G$14),0,'Parámetros Proyección'!$G$14)+IF((AF9/AI9>'Parámetros Proyección'!$G$15),0,'Parámetros Proyección'!$G$15))) | J9: =H9+I9 | K9: =P8 | L9: =K9*(1+'Parámetros Proyección'!$E$12) | M9: =L9*'Parámetros Proyección'!$F$12 | N9: =L9+M9 | O9: =IF((N9/AI9>'Parámetros Proyección'!$G$12),0,D9*'Parámetros Proyección'!$G$12/(IF((H9/AI9>'Parámetros Proyección'!$G$11),0,'Parámetros Proyección'!$G$11)+IF((N9/AI9>'Parámetros Proyección'!$G$12),0,'Parámetros Proyección'!$G$12)+IF((T9/AI9>'Parámetros Proyección'!$G$13),0,'Parámetros Proyección'!$G$13)+IF((Z9/AI9>'Parámetros Proyección'!$G$14),0,'Parámetros Proyección'!$G$14)+IF((AF9/AI9>'Parámetros Proyección'!$G$15),0,'Parámetros Proyección'!$G$15))) | P9: =N9+O9 | Q9: =V8 | R9: =Q9*(1+'Parámetros Proyección'!$E$13) | S9: =R9*'Parámetros Proyección'!$F$13 | T9: =R9+S9 | U9: =IF((T9/AI9>'Parámetros Proyección'!$G$13),0,D9*'Parámetros Proyección'!$G$13/(IF((H9/AI9>'Parámetros Proyección'!$G$11),0,'Parámetros Proyección'!$G$11)+IF((N9/AI9>'Parámetros Proyección'!$G$12),0,'Parámetros Proyección'!$G$12)+IF((T9/AI9>'Parámetros Proyección'!$G$13),0,'Parámetros Proyección'!$G$13)+IF((Z9/AI9>'Parámetros Proyección'!$G$14),0,'Parámetros Proyección'!$G$14)+IF((AF9/AI9>'Parámetros Proyección'!$G$15),0,'Parámetros Proyección'!$G$15))) | V9: =T9+U9 | W9: =AB8 | X9: =W9*(1+'Parámetros Proyección'!$E$14) | Y9: =X9*'Parámetros Proyección'!$F$14 | Z9: =X9+Y9 | AA9: =IF((Z9/AI9>'Parámetros Proyección'!$G$14),0,D9*'Parámetros Proyección'!$G$14/(IF((H9/AI9>'Parámetros Proyección'!$G$11),0,'Parámetros Proyección'!$G$11)+IF((N9/AI9>'Parámetros Proyección'!$G$12),0,'Parámetros Proyección'!$G$12)+IF((T9/AI9>'Parámetros Proyección'!$G$13),0,'Parámetros Proyección'!$G$13)+IF((Z9/AI9>'Parámetros Proyección'!$G$14),0,'Parámetros Proyección'!$G$14)+IF((AF9/AI9>'Parámetros Proyección'!$G$15),0,'Parámetros Proyección'!$G$15))) | AB9: =Z9+AA9 | AC9: =AH8 | AD9: =AC9*(1+'Parámetros Proyección'!$E$15) | AE9: =AD9*'Parámetros Proyección'!$F$15 | AF9: =AD9+AE9 | AG9: =IF((AF9/AI9>'Parámetros Proyección'!$G$15),0,D9*'Parámetros Proyección'!$G$15/(IF((H9/AI9>'Parámetros Proyección'!$G$11),0,'Parámetros Proyección'!$G$11)+IF((N9/AI9>'Parámetros Proyección'!$G$12),0,'Parámetros Proyección'!$G$12)+IF((T9/AI9>'Parámetros Proyección'!$G$13),0,'Parámetros Proyección'!$G$13)+IF((Z9/AI9>'Parámetros Proyección'!$G$14),0,'Parámetros Proyección'!$G$14)+IF((AF9/AI9>'Parámetros Proyección'!$G$15),0,'Parámetros Proyección'!$G$15))) | AH9: =AF9+AG9 | AI9: =H9+N9+T9+Z9+AF9 | AJ9: =AF9/AI9 | AK9: =IF(AJ9>'Parámetros Proyección'!$B$5,1,0) | AL9: =G9+M9+S9+Y9+AE9 | AM9: =AM8+D9 | AN9: =AN8+AL9 | AO9: =J9+P9+V9+AB9+AH9
A10: 7 | B10: =EDATE(B9,1) | C10: =YEAR(B10) | D10: ='Parámetros Proyección'!$B$3*(1+'Parámetros Proyección'!$B$4)^(C10-YEAR('Parámetros Proyección'!$B$6)) | E10: =J9 | F10: =E10*(1+'Parámetros Proyección'!$E$11) | G10: =F10*'Parámetros Proyección'!$F$11 | H10: =F10+G10 | I10: =IF((H10/AI10>'Parámetros Proyección'!$G$11),0,D10*'Parámetros Proyección'!$G$11/(IF((H10/AI10>'Parámetros Proyección'!$G$11),0,'Parámetros Proyección'!$G$11)+IF((N10/AI10>'Parámetros Proyección'!$G$12),0,'Parámetros Proyección'!$G$12)+IF((T10/AI10>'Parámetros Proyección'!$G$13),0,'Parámetros Proyección'!$G$13)+IF((Z10/AI10>'Parámetros Proyección'!$G$14),0,'Parámetros Proyección'!$G$14)+IF((AF10/AI10>'Parámetros Proyección'!$G$15),0,'Parámetros Proyección'!$G$15))) | J10: =H10+I10 | K10: =P9 | L10: =K10*(1+'Parámetros Proyección'!$E$12) | M10: =L10*'Parámetros Proyección'!$F$12 | N10: =L10+M10 | O10: =IF((N10/AI10>'Parámetros Proyección'!$G$12),0,D10*'Parámetros Proyección'!$G$12/(IF((H10/AI10>'Parámetros Proyección'!$G$11),0,'Parámetros Proyección'!$G$11)+IF((N10/AI10>'Parámetros Proyección'!$G$12),0,'Parámetros Proyección'!$G$12)+IF((T10/AI10>'Parámetros Proyección'!$G$13),0,'Parámetros Proyección'!$G$13)+IF((Z10/AI10>'Parámetros Proyección'!$G$14),0,'Parámetros Proyección'!$G$14)+IF((AF10/AI10>'Parámetros Proyección'!$G$15),0,'Parámetros Proyección'!$G$15))) | P10: =N10+O10 | Q10: =V9 | R10: =Q10*(1+'Parámetros Proyección'!$E$13) | S10: =R10*'Parámetros Proyección'!$F$13 | T10: =R10+S10 | U10: =IF((T10/AI10>'Parámetros Proyección'!$G$13),0,D10*'Parámetros Proyección'!$G$13/(IF((H10/AI10>'Parámetros Proyección'!$G$11),0,'Parámetros Proyección'!$G$11)+IF((N10/AI10>'Parámetros Proyección'!$G$12),0,'Parámetros Proyección'!$G$12)+IF((T10/AI10>'Parámetros Proyección'!$G$13),0,'Parámetros Proyección'!$G$13)+IF((Z10/AI10>'Parámetros Proyección'!$G$14),0,'Parámetros Proyección'!$G$14)+IF((AF10/AI10>'Parámetros Proyección'!$G$15),0,'Parámetros Proyección'!$G$15))) | V10: =T10+U10 | W10: =AB9 | X10: =W10*(1+'Parámetros Proyección'!$E$14) | Y10: =X10*'Parámetros Proyección'!$F$14 | Z10: =X10+Y10 | AA10: =IF((Z10/AI10>'Parámetros Proyección'!$G$14),0,D10*'Parámetros Proyección'!$G$14/(IF((H10/AI10>'Parámetros Proyección'!$G$11),0,'Parámetros Proyección'!$G$11)+IF((N10/AI10>'Parámetros Proyección'!$G$12),0,'Parámetros Proyección'!$G$12)+IF((T10/AI10>'Parámetros Proyección'!$G$13),0,'Parámetros Proyección'!$G$13)+IF((Z10/AI10>'Parámetros Proyección'!$G$14),0,'Parámetros Proyección'!$G$14)+IF((AF10/AI10>'Parámetros Proyección'!$G$15),0,'Parámetros Proyección'!$G$15))) | AB10: =Z10+AA10 | AC10: =AH9 | AD10: =AC10*(1+'Parámetros Proyección'!$E$15) | AE10: =AD10*'Parámetros Proyección'!$F$15 | AF10: =AD10+AE10 | AG10: =IF((AF10/AI10>'Parámetros Proyección'!$G$15),0,D10*'Parámetros Proyección'!$G$15/(IF((H10/AI10>'Parámetros Proyección'!$G$11),0,'Parámetros Proyección'!$G$11)+IF((N10/AI10>'Parámetros Proyección'!$G$12),0,'Parámetros Proyección'!$G$12)+IF((T10/AI10>'Parámetros Proyección'!$G$13),0,'Parámetros Proyección'!$G$13)+IF((Z10/AI10>'Parámetros Proyección'!$G$14),0,'Parámetros Proyección'!$G$14)+IF((AF10/AI10>'Parámetros Proyección'!$G$15),0,'Parámetros Proyección'!$G$15))) | AH10: =AF10+AG10 | AI10: =H10+N10+T10+Z10+AF10 | AJ10: =AF10/AI10 | AK10: =IF(AJ10>'Parámetros Proyección'!$B$5,1,0) | AL10: =G10+M10+S10+Y10+AE10 | AM10: =AM9+D10 | AN10: =AN9+AL10 | AO10: =J10+P10+V10+AB10+AH10
A11: 8 | B11: =EDATE(B10,1) | C11: =YEAR(B11) | D11: ='Parámetros Proyección'!$B$3*(1+'Parámetros Proyección'!$B$4)^(C11-YEAR('Parámetros Proyección'!$B$6)) | E11: =J10 | F11: =E11*(1+'Parámetros Proyección'!$E$11) | G11: =F11*'Parámetros Proyección'!$F$11 | H11: =F11+G11 | I11: =IF((H11/AI11>'Parámetros Proyección'!$G$11),0,D11*'Parámetros Proyección'!$G$11/(IF((H11/AI11>'Parámetros Proyección'!$G$11),0,'Parámetros Proyección'!$G$11)+IF((N11/AI11>'Parámetros Proyección'!$G$12),0,'Parámetros Proyección'!$G$12)+IF((T11/AI11>'Parámetros Proyección'!$G$13),0,'Parámetros Proyección'!$G$13)+IF((Z11/AI11>'Parámetros Proyección'!$G$14),0,'Parámetros Proyección'!$G$14)+IF((AF11/AI11>'Parámetros Proyección'!$G$15),0,'Parámetros Proyección'!$G$15))) | J11: =H11+I11 | K11: =P10 | L11: =K11*(1+'Parámetros Proyección'!$E$12) | M11: =L11*'Parámetros Proyección'!$F$12 | N11: =L11+M11 | O11: =IF((N11/AI11>'Parámetros Proyección'!$G$12),0,D11*'Parámetros Proyección'!$G$12/(IF((H11/AI11>'Parámetros Proyección'!$G$11),0,'Parámetros Proyección'!$G$11)+IF((N11/AI11>'Parámetros Proyección'!$G$12),0,'Parámetros Proyección'!$G$12)+IF((T11/AI11>'Parámetros Proyección'!$G$13),0,'Parámetros Proyección'!$G$13)+IF((Z11/AI11>'Parámetros Proyección'!$G$14),0,'Parámetros Proyección'!$G$14)+IF((AF11/AI11>'Parámetros Proyección'!$G$15),0,'Parámetros Proyección'!$G$15))) | P11: =N11+O11 | Q11: =V10 | R11: =Q11*(1+'Parámetros Proyección'!$E$13) | S11: =R11*'Parámetros Proyección'!$F$13 | T11: =R11+S11 | U11: =IF((T11/AI11>'Parámetros Proyección'!$G$13),0,D11*'Parámetros Proyección'!$G$13/(IF((H11/AI11>'Parámetros Proyección'!$G$11),0,'Parámetros Proyección'!$G$11)+IF((N11/AI11>'Parámetros Proyección'!$G$12),0,'Parámetros Proyección'!$G$12)+IF((T11/AI11>'Parámetros Proyección'!$G$13),0,'Parámetros Proyección'!$G$13)+IF((Z11/AI11>'Parámetros Proyección'!$G$14),0,'Parámetros Proyección'!$G$14)+IF((AF11/AI11>'Parámetros Proyección'!$G$15),0,'Parámetros Proyección'!$G$15))) | V11: =T11+U11 | W11: =AB10 | X11: =W11*(1+'Parámetros Proyección'!$E$14) | Y11: =X11*'Parámetros Proyección'!$F$14 | Z11: =X11+Y11 | AA11: =IF((Z11/AI11>'Parámetros Proyección'!$G$14),0,D11*'Parámetros Proyección'!$G$14/(IF((H11/AI11>'Parámetros Proyección'!$G$11),0,'Parámetros Proyección'!$G$11)+IF((N11/AI11>'Parámetros Proyección'!$G$12),0,'Parámetros Proyección'!$G$12)+IF((T11/AI11>'Parámetros Proyección'!$G$13),0,'Parámetros Proyección'!$G$13)+IF((Z11/AI11>'Parámetros Proyección'!$G$14),0,'Parámetros Proyección'!$G$14)+IF((AF11/AI11>'Parámetros Proyección'!$G$15),0,'Parámetros Proyección'!$G$15))) | AB11: =Z11+AA11 | AC11: =AH10 | AD11: =AC11*(1+'Parámetros Proyección'!$E$15) | AE11: =AD11*'Parámetros Proyección'!$F$15 | AF11: =AD11+AE11 | AG11: =IF((AF11/AI11>'Parámetros Proyección'!$G$15),0,D11*'Parámetros Proyección'!$G$15/(IF((H11/AI11>'Parámetros Proyección'!$G$11),0,'Parámetros Proyección'!$G$11)+IF((N11/AI11>'Parámetros Proyección'!$G$12),0,'Parámetros Proyección'!$G$12)+IF((T11/AI11>'Parámetros Proyección'!$G$13),0,'Parámetros Proyección'!$G$13)+IF((Z11/AI11>'Parámetros Proyección'!$G$14),0,'Parámetros Proyección'!$G$14)+IF((AF11/AI11>'Parámetros Proyección'!$G$15),0,'Parámetros Proyección'!$G$15))) | AH11: =AF11+AG11 | AI11: =H11+N11+T11+Z11+AF11 | AJ11: =AF11/AI11 | AK11: =IF(AJ11>'Parámetros Proyección'!$B$5,1,0) | AL11: =G11+M11+S11+Y11+AE11 | AM11: =AM10+D11 | AN11: =AN10+AL11 | AO11: =J11+P11+V11+AB11+AH11
A12: 9 | B12: =EDATE(B11,1) | C12: =YEAR(B12) | D12: ='Parámetros Proyección'!$B$3*(1+'Parámetros Proyección'!$B$4)^(C12-YEAR('Parámetros Proyección'!$B$6)) | E12: =J11 | F12: =E12*(1+'Parámetros Proyección'!$E$11) | G12: =F12*'Parámetros Proyección'!$F$11 | H12: =F12+G12 | I12: =IF((H12/AI12>'Parámetros Proyección'!$G$11),0,D12*'Parámetros Proyección'!$G$11/(IF((H12/AI12>'Parámetros Proyección'!$G$11),0,'Parámetros Proyección'!$G$11)+IF((N12/AI12>'Parámetros Proyección'!$G$12),0,'Parámetros Proyección'!$G$12)+IF((T12/AI12>'Parámetros Proyección'!$G$13),0,'Parámetros Proyección'!$G$13)+IF((Z12/AI12>'Parámetros Proyección'!$G$14),0,'Parámetros Proyección'!$G$14)+IF((AF12/AI12>'Parámetros Proyección'!$G$15),0,'Parámetros Proyección'!$G$15))) | J12: =H12+I12 | K12: =P11 | L12: =K12*(1+'Parámetros Proyección'!$E$12) | M12: =L12*'Parámetros Proyección'!$F$12 | N12: =L12+M12 | O12: =IF((N12/AI12>'Parámetros Proyección'!$G$12),0,D12*'Parámetros Proyección'!$G$12/(IF((H12/AI12>'Parámetros Proyección'!$G$11),0,'Parámetros Proyección'!$G$11)+IF((N12/AI12>'Parámetros Proyección'!$G$12),0,'Parámetros Proyección'!$G$12)+IF((T12/AI12>'Parámetros Proyección'!$G$13),0,'Parámetros Proyección'!$G$13)+IF((Z12/AI12>'Parámetros Proyección'!$G$14),0,'Parámetros Proyección'!$G$14)+IF((AF12/AI12>'Parámetros Proyección'!$G$15),0,'Parámetros Proyección'!$G$15))) | P12: =N12+O12 | Q12: =V11 | R12: =Q12*(1+'Parámetros Proyección'!$E$13) | S12: =R12*'Parámetros Proyección'!$F$13 | T12: =R12+S12 | U12: =IF((T12/AI12>'Parámetros Proyección'!$G$13),0,D12*'Parámetros Proyección'!$G$13/(IF((H12/AI12>'Parámetros Proyección'!$G$11),0,'Parámetros Proyección'!$G$11)+IF((N12/AI12>'Parámetros Proyección'!$G$12),0,'Parámetros Proyección'!$G$12)+IF((T12/AI12>'Parámetros Proyección'!$G$13),0,'Parámetros Proyección'!$G$13)+IF((Z12/AI12>'Parámetros Proyección'!$G$14),0,'Parámetros Proyección'!$G$14)+IF((AF12/AI12>'Parámetros Proyección'!$G$15),0,'Parámetros Proyección'!$G$15))) | V12: =T12+U12 | W12: =AB11 | X12: =W12*(1+'Parámetros Proyección'!$E$14) | Y12: =X12*'Parámetros Proyección'!$F$14 | Z12: =X12+Y12 | AA12: =IF((Z12/AI12>'Parámetros Proyección'!$G$14),0,D12*'Parámetros Proyección'!$G$14/(IF((H12/AI12>'Parámetros Proyección'!$G$11),0,'Parámetros Proyección'!$G$11)+IF((N12/AI12>'Parámetros Proyección'!$G$12),0,'Parámetros Proyección'!$G$12)+IF((T12/AI12>'Parámetros Proyección'!$G$13),0,'Parámetros Proyección'!$G$13)+IF((Z12/AI12>'Parámetros Proyección'!$G$14),0,'Parámetros Proyección'!$G$14)+IF((AF12/AI12>'Parámetros Proyección'!$G$15),0,'Parámetros Proyección'!$G$15))) | AB12: =Z12+AA12 | AC12: =AH11 | AD12: =AC12*(1+'Parámetros Proyección'!$E$15) | AE12: =AD12*'Parámetros Proyección'!$F$15 | AF12: =AD12+AE12 | AG12: =IF((AF12/AI12>'Parámetros Proyección'!$G$15),0,D12*'Parámetros Proyección'!$G$15/(IF((H12/AI12>'Parámetros Proyección'!$G$11),0,'Parámetros Proyección'!$G$11)+IF((N12/AI12>'Parámetros Proyección'!$G$12),0,'Parámetros Proyección'!$G$12)+IF((T12/AI12>'Parámetros Proyección'!$G$13),0,'Parámetros Proyección'!$G$13)+IF((Z12/AI12>'Parámetros Proyección'!$G$14),0,'Parámetros Proyección'!$G$14)+IF((AF12/AI12>'Parámetros Proyección'!$G$15),0,'Parámetros Proyección'!$G$15))) | AH12: =AF12+AG12 | AI12: =H12+N12+T12+Z12+AF12 | AJ12: =AF12/AI12 | AK12: =IF(AJ12>'Parámetros Proyección'!$B$5,1,0) | AL12: =G12+M12+S12+Y12+AE12 | AM12: =AM11+D12 | AN12: =AN11+AL12 | AO12: =J12+P12+V12+AB12+AH12
A13: 10 | B13: =EDATE(B12,1) | C13: =YEAR(B13) | D13: ='Parámetros Proyección'!$B$3*(1+'Parámetros Proyección'!$B$4)^(C13-YEAR('Parámetros Proyección'!$B$6)) | E13: =J12 | F13: =E13*(1+'Parámetros Proyección'!$E$11) | G13: =F13*'Parámetros Proyección'!$F$11 | H13: =F13+G13 | I13: =IF((H13/AI13>'Parámetros Proyección'!$G$11),0,D13*'Parámetros Proyección'!$G$11/(IF((H13/AI13>'Parámetros Proyección'!$G$11),0,'Parámetros Proyección'!$G$11)+IF((N13/AI13>'Parámetros Proyección'!$G$12),0,'Parámetros Proyección'!$G$12)+IF((T13/AI13>'Parámetros Proyección'!$G$13),0,'Parámetros Proyección'!$G$13)+IF((Z13/AI13>'Parámetros Proyección'!$G$14),0,'Parámetros Proyección'!$G$14)+IF((AF13/AI13>'Parámetros Proyección'!$G$15),0,'Parámetros Proyección'!$G$15))) | J13: =H13+I13 | K13: =P12 | L13: =K13*(1+'Parámetros Proyección'!$E$12) | M13: =L13*'Parámetros Proyección'!$F$12 | N13: =L13+M13 | O13: =IF((N13/AI13>'Parámetros Proyección'!$G$12),0,D13*'Parámetros Proyección'!$G$12/(IF((H13/AI13>'Parámetros Proyección'!$G$11),0,'Parámetros Proyección'!$G$11)+IF((N13/AI13>'Parámetros Proyección'!$G$12),0,'Parámetros Proyección'!$G$12)+IF((T13/AI13>'Parámetros Proyección'!$G$13),0,'Parámetros Proyección'!$G$13)+IF((Z13/AI13>'Parámetros Proyección'!$G$14),0,'Parámetros Proyección'!$G$14)+IF((AF13/AI13>'Parámetros Proyección'!$G$15),0,'Parámetros Proyección'!$G$15))) | P13: =N13+O13 | Q13: =V12 | R13: =Q13*(1+'Parámetros Proyección'!$E$13) | S13: =R13*'Parámetros Proyección'!$F$13 | T13: =R13+S13 | U13: =IF((T13/AI13>'Parámetros Proyección'!$G$13),0,D13*'Parámetros Proyección'!$G$13/(IF((H13/AI13>'Parámetros Proyección'!$G$11),0,'Parámetros Proyección'!$G$11)+IF((N13/AI13>'Parámetros Proyección'!$G$12),0,'Parámetros Proyección'!$G$12)+IF((T13/AI13>'Parámetros Proyección'!$G$13),0,'Parámetros Proyección'!$G$13)+IF((Z13/AI13>'Parámetros Proyección'!$G$14),0,'Parámetros Proyección'!$G$14)+IF((AF13/AI13>'Parámetros Proyección'!$G$15),0,'Parámetros Proyección'!$G$15))) | V13: =T13+U13 | W13: =AB12 | X13: =W13*(1+'Parámetros Proyección'!$E$14) | Y13: =X13*'Parámetros Proyección'!$F$14 | Z13: =X13+Y13 | AA13: =IF((Z13/AI13>'Parámetros Proyección'!$G$14),0,D13*'Parámetros Proyección'!$G$14/(IF((H13/AI13>'Parámetros Proyección'!$G$11),0,'Parámetros Proyección'!$G$11)+IF((N13/AI13>'Parámetros Proyección'!$G$12),0,'Parámetros Proyección'!$G$12)+IF((T13/AI13>'Parámetros Proyección'!$G$13),0,'Parámetros Proyección'!$G$13)+IF((Z13/AI13>'Parámetros Proyección'!$G$14),0,'Parámetros Proyección'!$G$14)+IF((AF13/AI13>'Parámetros Proyección'!$G$15),0,'Parámetros Proyección'!$G$15))) | AB13: =Z13+AA13 | AC13: =AH12 | AD13: =AC13*(1+'Parámetros Proyección'!$E$15) | AE13: =AD13*'Parámetros Proyección'!$F$15 | AF13: =AD13+AE13 | AG13: =IF((AF13/AI13>'Parámetros Proyección'!$G$15),0,D13*'Parámetros Proyección'!$G$15/(IF((H13/AI13>'Parámetros Proyección'!$G$11),0,'Parámetros Proyección'!$G$11)+IF((N13/AI13>'Parámetros Proyección'!$G$12),0,'Parámetros Proyección'!$G$12)+IF((T13/AI13>'Parámetros Proyección'!$G$13),0,'Parámetros Proyección'!$G$13)+IF((Z13/AI13>'Parámetros Proyección'!$G$14),0,'Parámetros Proyección'!$G$14)+IF((AF13/AI13>'Parámetros Proyección'!$G$15),0,'Parámetros Proyección'!$G$15))) | AH13: =AF13+AG13 | AI13: =H13+N13+T13+Z13+AF13 | AJ13: =AF13/AI13 | AK13: =IF(AJ13>'Parámetros Proyección'!$B$5,1,0) | AL13: =G13+M13+S13+Y13+AE13 | AM13: =AM12+D13 | AN13: =AN12+AL13 | AO13: =J13+P13+V13+AB13+AH13
A14: 11 | B14: =EDATE(B13,1) | C14: =YEAR(B14) | D14: ='Parámetros Proyección'!$B$3*(1+'Parámetros Proyección'!$B$4)^(C14-YEAR('Parámetros Proyección'!$B$6)) | E14: =J13 | F14: =E14*(1+'Parámetros Proyección'!$E$11) | G14: =F14*'Parámetros Proyección'!$F$11 | H14: =F14+G14 | I14: =IF((H14/AI14>'Parámetros Proyección'!$G$11),0,D14*'Parámetros Proyección'!$G$11/(IF((H14/AI14>'Parámetros Proyección'!$G$11),0,'Parámetros Proyección'!$G$11)+IF((N14/AI14>'Parámetros Proyección'!$G$12),0,'Parámetros Proyección'!$G$12)+IF((T14/AI14>'Parámetros Proyección'!$G$13),0,'Parámetros Proyección'!$G$13)+IF((Z14/AI14>'Parámetros Proyección'!$G$14),0,'Parámetros Proyección'!$G$14)+IF((AF14/AI14>'Parámetros Proyección'!$G$15),0,'Parámetros Proyección'!$G$15))) | J14: =H14+I14 | K14: =P13 | L14: =K14*(1+'Parámetros Proyección'!$E$12) | M14: =L14*'Parámetros Proyección'!$F$12 | N14: =L14+M14 | O14: =IF((N14/AI14>'Parámetros Proyección'!$G$12),0,D14*'Parámetros Proyección'!$G$12/(IF((H14/AI14>'Parámetros Proyección'!$G$11),0,'Parámetros Proyección'!$G$11)+IF((N14/AI14>'Parámetros Proyección'!$G$12),0,'Parámetros Proyección'!$G$12)+IF((T14/AI14>'Parámetros Proyección'!$G$13),0,'Parámetros Proyección'!$G$13)+IF((Z14/AI14>'Parámetros Proyección'!$G$14),0,'Parámetros Proyección'!$G$14)+IF((AF14/AI14>'Parámetros Proyección'!$G$15),0,'Parámetros Proyección'!$G$15))) | P14: =N14+O14 | Q14: =V13 | R14: =Q14*(1+'Parámetros Proyección'!$E$13) | S14: =R14*'Parámetros Proyección'!$F$13 | T14: =R14+S14 | U14: =IF((T14/AI14>'Parámetros Proyección'!$G$13),0,D14*'Parámetros Proyección'!$G$13/(IF((H14/AI14>'Parámetros Proyección'!$G$11),0,'Parámetros Proyección'!$G$11)+IF((N14/AI14>'Parámetros Proyección'!$G$12),0,'Parámetros Proyección'!$G$12)+IF((T14/AI14>'Parámetros Proyección'!$G$13),0,'Parámetros Proyección'!$G$13)+IF((Z14/AI14>'Parámetros Proyección'!$G$14),0,'Parámetros Proyección'!$G$14)+IF((AF14/AI14>'Parámetros Proyección'!$G$15),0,'Parámetros Proyección'!$G$15))) | V14: =T14+U14 | W14: =AB13 | X14: =W14*(1+'Parámetros Proyección'!$E$14) | Y14: =X14*'Parámetros Proyección'!$F$14 | Z14: =X14+Y14 | AA14: =IF((Z14/AI14>'Parámetros Proyección'!$G$14),0,D14*'Parámetros Proyección'!$G$14/(IF((H14/AI14>'Parámetros Proyección'!$G$11),0,'Parámetros Proyección'!$G$11)+IF((N14/AI14>'Parámetros Proyección'!$G$12),0,'Parámetros Proyección'!$G$12)+IF((T14/AI14>'Parámetros Proyección'!$G$13),0,'Parámetros Proyección'!$G$13)+IF((Z14/AI14>'Parámetros Proyección'!$G$14),0,'Parámetros Proyección'!$G$14)+IF((AF14/AI14>'Parámetros Proyección'!$G$15),0,'Parámetros Proyección'!$G$15))) | AB14: =Z14+AA14 | AC14: =AH13 | AD14: =AC14*(1+'Parámetros Proyección'!$E$15) | AE14: =AD14*'Parámetros Proyección'!$F$15 | AF14: =AD14+AE14 | AG14: =IF((AF14/AI14>'Parámetros Proyección'!$G$15),0,D14*'Parámetros Proyección'!$G$15/(IF((H14/AI14>'Parámetros Proyección'!$G$11),0,'Parámetros Proyección'!$G$11)+IF((N14/AI14>'Parámetros Proyección'!$G$12),0,'Parámetros Proyección'!$G$12)+IF((T14/AI14>'Parámetros Proyección'!$G$13),0,'Parámetros Proyección'!$G$13)+IF((Z14/AI14>'Parámetros Proyección'!$G$14),0,'Parámetros Proyección'!$G$14)+IF((AF14/AI14>'Parámetros Proyección'!$G$15),0,'Parámetros Proyección'!$G$15))) | AH14: =AF14+AG14 | AI14: =H14+N14+T14+Z14+AF14 | AJ14: =AF14/AI14 | AK14: =IF(AJ14>'Parámetros Proyección'!$B$5,1,0) | AL14: =G14+M14+S14+Y14+AE14 | AM14: =AM13+D14 | AN14: =AN13+AL14 | AO14: =J14+P14+V14+AB14+AH14
A15: 12 | B15: =EDATE(B14,1) | C15: =YEAR(B15) | D15: ='Parámetros Proyección'!$B$3*(1+'Parámetros Proyección'!$B$4)^(C15-YEAR('Parámetros Proyección'!$B$6)) | E15: =J14 | F15: =E15*(1+'Parámetros Proyección'!$E$11) | G15: =F15*'Parámetros Proyección'!$F$11 | H15: =F15+G15 | I15: =IF((H15/AI15>'Parámetros Proyección'!$G$11),0,D15*'Parámetros Proyección'!$G$11/(IF((H15/AI15>'Parámetros Proyección'!$G$11),0,'Parámetros Proyección'!$G$11)+IF((N15/AI15>'Parámetros Proyección'!$G$12),0,'Parámetros Proyección'!$G$12)+IF((T15/AI15>'Parámetros Proyección'!$G$13),0,'Parámetros Proyección'!$G$13)+IF((Z15/AI15>'Parámetros Proyección'!$G$14),0,'Parámetros Proyección'!$G$14)+IF((AF15/AI15>'Parámetros Proyección'!$G$15),0,'Parámetros Proyección'!$G$15))) | J15: =H15+I15 | K15: =P14 | L15: =K15*(1+'Parámetros Proyección'!$E$12) | M15: =L15*'Parámetros Proyección'!$F$12 | N15: =L15+M15 | O15: =IF((N15/AI15>'Parámetros Proyección'!$G$12),0,D15*'Parámetros Proyección'!$G$12/(IF((H15/AI15>'Parámetros Proyección'!$G$11),0,'Parámetros Proyección'!$G$11)+IF((N15/AI15>'Parámetros Proyección'!$G$12),0,'Parámetros Proyección'!$G$12)+IF((T15/AI15>'Parámetros Proyección'!$G$13),0,'Parámetros Proyección'!$G$13)+IF((Z15/AI15>'Parámetros Proyección'!$G$14),0,'Parámetros Proyección'!$G$14)+IF((AF15/AI15>'Parámetros Proyección'!$G$15),0,'Parámetros Proyección'!$G$15))) | P15: =N15+O15 | Q15: =V14 | R15: =Q15*(1+'Parámetros Proyección'!$E$13) | S15: =R15*'Parámetros Proyección'!$F$13 | T15: =R15+S15 | U15: =IF((T15/AI15>'Parámetros Proyección'!$G$13),0,D15*'Parámetros Proyección'!$G$13/(IF((H15/AI15>'Parámetros Proyección'!$G$11),0,'Parámetros Proyección'!$G$11)+IF((N15/AI15>'Parámetros Proyección'!$G$12),0,'Parámetros Proyección'!$G$12)+IF((T15/AI15>'Parámetros Proyección'!$G$13),0,'Parámetros Proyección'!$G$13)+IF((Z15/AI15>'Parámetros Proyección'!$G$14),0,'Parámetros Proyección'!$G$14)+IF((AF15/AI15>'Parámetros Proyección'!$G$15),0,'Parámetros Proyección'!$G$15))) | V15: =T15+U15 | W15: =AB14 | X15: =W15*(1+'Parámetros Proyección'!$E$14) | Y15: =X15*'Parámetros Proyección'!$F$14 | Z15: =X15+Y15 | AA15: =IF((Z15/AI15>'Parámetros Proyección'!$G$14),0,D15*'Parámetros Proyección'!$G$14/(IF((H15/AI15>'Parámetros Proyección'!$G$11),0,'Parámetros Proyección'!$G$11)+IF((N15/AI15>'Parámetros Proyección'!$G$12),0,'Parámetros Proyección'!$G$12)+IF((T15/AI15>'Parámetros Proyección'!$G$13),0,'Parámetros Proyección'!$G$13)+IF((Z15/AI15>'Parámetros Proyección'!$G$14),0,'Parámetros Proyección'!$G$14)+IF((AF15/AI15>'Parámetros Proyección'!$G$15),0,'Parámetros Proyección'!$G$15))) | AB15: =Z15+AA15 | AC15: =AH14 | AD15: =AC15*(1+'Parámetros Proyección'!$E$15) | AE15: =AD15*'Parámetros Proyección'!$F$15 | AF15: =AD15+AE15 | AG15: =IF((AF15/AI15>'Parámetros Proyección'!$G$15),0,D15*'Parámetros Proyección'!$G$15/(IF((H15/AI15>'Parámetros Proyección'!$G$11),0,'Parámetros Proyección'!$G$11)+IF((N15/AI15>'Parámetros Proyección'!$G$12),0,'Parámetros Proyección'!$G$12)+IF((T15/AI15>'Parámetros Proyección'!$G$13),0,'Parámetros Proyección'!$G$13)+IF((Z15/AI15>'Parámetros Proyección'!$G$14),0,'Parámetros Proyección'!$G$14)+IF((AF15/AI15>'Parámetros Proyección'!$G$15),0,'Parámetros Proyección'!$G$15))) | AH15: =AF15+AG15 | AI15: =H15+N15+T15+Z15+AF15 | AJ15: =AF15/AI15 | AK15: =IF(AJ15>'Parámetros Proyección'!$B$5,1,0) | AL15: =G15+M15+S15+Y15+AE15 | AM15: =AM14+D15 | AN15: =AN14+AL15 | AO15: =J15+P15+V15+AB15+AH15
A16: 13 | B16: =EDATE(B15,1) | C16: =YEAR(B16) | D16: ='Parámetros Proyección'!$B$3*(1+'Parámetros Proyección'!$B$4)^(C16-YEAR('Parámetros Proyección'!$B$6)) | E16: =J15 | F16: =E16*(1+'Parámetros Proyección'!$E$11) | G16: =F16*'Parámetros Proyección'!$F$11 | H16: =F16+G16 | I16: =IF((H16/AI16>'Parámetros Proyección'!$G$11),0,D16*'Parámetros Proyección'!$G$11/(IF((H16/AI16>'Parámetros Proyección'!$G$11),0,'Parámetros Proyección'!$G$11)+IF((N16/AI16>'Parámetros Proyección'!$G$12),0,'Parámetros Proyección'!$G$12)+IF((T16/AI16>'Parámetros Proyección'!$G$13),0,'Parámetros Proyección'!$G$13)+IF((Z16/AI16>'Parámetros Proyección'!$G$14),0,'Parámetros Proyección'!$G$14)+IF((AF16/AI16>'Parámetros Proyección'!$G$15),0,'Parámetros Proyección'!$G$15))) | J16: =H16+I16 | K16: =P15 | L16: =K16*(1+'Parámetros Proyección'!$E$12) | M16: =L16*'Parámetros Proyección'!$F$12 | N16: =L16+M16 | O16: =IF((N16/AI16>'Parámetros Proyección'!$G$12),0,D16*'Parámetros Proyección'!$G$12/(IF((H16/AI16>'Parámetros Proyección'!$G$11),0,'Parámetros Proyección'!$G$11)+IF((N16/AI16>'Parámetros Proyección'!$G$12),0,'Parámetros Proyección'!$G$12)+IF((T16/AI16>'Parámetros Proyección'!$G$13),0,'Parámetros Proyección'!$G$13)+IF((Z16/AI16>'Parámetros Proyección'!$G$14),0,'Parámetros Proyección'!$G$14)+IF((AF16/AI16>'Parámetros Proyección'!$G$15),0,'Parámetros Proyección'!$G$15))) | P16: =N16+O16 | Q16: =V15 | R16: =Q16*(1+'Parámetros Proyección'!$E$13) | S16: =R16*'Parámetros Proyección'!$F$13 | T16: =R16+S16 | U16: =IF((T16/AI16>'Parámetros Proyección'!$G$13),0,D16*'Parámetros Proyección'!$G$13/(IF((H16/AI16>'Parámetros Proyección'!$G$11),0,'Parámetros Proyección'!$G$11)+IF((N16/AI16>'Parámetros Proyección'!$G$12),0,'Parámetros Proyección'!$G$12)+IF((T16/AI16>'Parámetros Proyección'!$G$13),0,'Parámetros Proyección'!$G$13)+IF((Z16/AI16>'Parámetros Proyección'!$G$14),0,'Parámetros Proyección'!$G$14)+IF((AF16/AI16>'Parámetros Proyección'!$G$15),0,'Parámetros Proyección'!$G$15))) | V16: =T16+U16 | W16: =AB15 | X16: =W16*(1+'Parámetros Proyección'!$E$14) | Y16: =X16*'Parámetros Proyección'!$F$14 | Z16: =X16+Y16 | AA16: =IF((Z16/AI16>'Parámetros Proyección'!$G$14),0,D16*'Parámetros Proyección'!$G$14/(IF((H16/AI16>'Parámetros Proyección'!$G$11),0,'Parámetros Proyección'!$G$11)+IF((N16/AI16>'Parámetros Proyección'!$G$12),0,'Parámetros Proyección'!$G$12)+IF((T16/AI16>'Parámetros Proyección'!$G$13),0,'Parámetros Proyección'!$G$13)+IF((Z16/AI16>'Parámetros Proyección'!$G$14),0,'Parámetros Proyección'!$G$14)+IF((AF16/AI16>'Parámetros Proyección'!$G$15),0,'Parámetros Proyección'!$G$15))) | AB16: =Z16+AA16 | AC16: =AH15 | AD16: =AC16*(1+'Parámetros Proyección'!$E$15) | AE16: =AD16*'Parámetros Proyección'!$F$15 | AF16: =AD16+AE16 | AG16: =IF((AF16/AI16>'Parámetros Proyección'!$G$15),0,D16*'Parámetros Proyección'!$G$15/(IF((H16/AI16>'Parámetros Proyección'!$G$11),0,'Parámetros Proyección'!$G$11)+IF((N16/AI16>'Parámetros Proyección'!$G$12),0,'Parámetros Proyección'!$G$12)+IF((T16/AI16>'Parámetros Proyección'!$G$13),0,'Parámetros Proyección'!$G$13)+IF((Z16/AI16>'Parámetros Proyección'!$G$14),0,'Parámetros Proyección'!$G$14)+IF((AF16/AI16>'Parámetros Proyección'!$G$15),0,'Parámetros Proyección'!$G$15))) | AH16: =AF16+AG16 | AI16: =H16+N16+T16+Z16+AF16 | AJ16: =AF16/AI16 | AK16: =IF(AJ16>'Parámetros Proyección'!$B$5,1,0) | AL16: =G16+M16+S16+Y16+AE16 | AM16: =AM15+D16 | AN16: =AN15+AL16 | AO16: =J16+P16+V16+AB16+AH16
... A423: 420 | B423: =EDATE(B422,1) | C423: =YEAR(B423) | D423: ='Parámetros Proyección'!$B$3*(1+'Parámetros Proyección'!$B$4)^(C423-YEAR('Parámetros Proyección'!$B$6)) | E423: =J422 | F423: =E423*(1+'Parámetros Proyección'!$E$11) | G423: =F423*'Parámetros Proyección'!$F$11 | H423: =F423+G423 | I423: =IF((H423/AI423>'Parámetros Proyección'!$G$11),0,D423*'Parámetros Proyección'!$G$11/(IF((H423/AI423>'Parámetros Proyección'!$G$11),0,'Parámetros Proyección'!$G$11)+IF((N423/AI423>'Parámetros Proyección'!$G$12),0,'Parámetros Proyección'!$G$12)+IF((T423/AI423>'Parámetros Proyección'!$G$13),0,'Parámetros Proyección'!$G$13)+IF((Z423/AI423>'Parámetros Proyección'!$G$14),0,'Parámetros Proyección'!$G$14)+IF((AF423/AI423>'Parámetros Proyección'!$G$15),0,'Parámetros Proyección'!$G$15))) | J423: =H423+I423 | K423: =P422 | L423: =K423*(1+'Parámetros Proyección'!$E$12) | M423: =L423*'Parámetros Proyección'!$F$12 | N423: =L423+M423 | O423: =IF((N423/AI423>'Parámetros Proyección'!$G$12),0,D423*'Parámetros Proyección'!$G$12/(IF((H423/AI423>'Parámetros Proyección'!$G$11),0,'Parámetros Proyección'!$G$11)+IF((N423/AI423>'Parámetros Proyección'!$G$12),0,'Parámetros Proyección'!$G$12)+IF((T423/AI423>'Parámetros Proyección'!$G$13),0,'Parámetros Proyección'!$G$13)+IF((Z423/AI423>'Parámetros Proyección'!$G$14),0,'Parámetros Proyección'!$G$14)+IF((AF423/AI423>'Parámetros Proyección'!$G$15),0,'Parámetros Proyección'!$G$15))) | P423: =N423+O423 | Q423: =V422 | R423: =Q423*(1+'Parámetros Proyección'!$E$13) | S423: =R423*'Parámetros Proyección'!$F$13 | T423: =R423+S423 | U423: =IF((T423/AI423>'Parámetros Proyección'!$G$13),0,D423*'Parámetros Proyección'!$G$13/(IF((H423/AI423>'Parámetros Proyección'!$G$11),0,'Parámetros Proyección'!$G$11)+IF((N423/AI423>'Parámetros Proyección'!$G$12),0,'Parámetros Proyección'!$G$12)+IF((T423/AI423>'Parámetros Proyección'!$G$13),0,'Parámetros Proyección'!$G$13)+IF((Z423/AI423>'Parámetros Proyección'!$G$14),0,'Parámetros Proyección'!$G$14)+IF((AF423/AI423>'Parámetros Proyección'!$G$15),0,'Parámetros Proyección'!$G$15))) | V423: =T423+U423 | W423: =AB422 | X423: =W423*(1+'Parámetros Proyección'!$E$14) | Y423: =X423*'Parámetros Proyección'!$F$14 | Z423: =X423+Y423 | AA423: =IF((Z423/AI423>'Parámetros Proyección'!$G$14),0,D423*'Parámetros Proyección'!$G$14/(IF((H423/AI423>'Parámetros Proyección'!$G$11),0,'Parámetros Proyección'!$G$11)+IF((N423/AI423>'Parámetros Proyección'!$G$12),0,'Parámetros Proyección'!$G$12)+IF((T423/AI423>'Parámetros Proyección'!$G$13),0,'Parámetros Proyección'!$G$13)+IF((Z423/AI423>'Parámetros Proyección'!$G$14),0,'Parámetros Proyección'!$G$14)+IF((AF423/AI423>'Parámetros Proyección'!$G$15),0,'Parámetros Proyección'!$G$15))) | AB423: =Z423+AA423 | AC423: =AH422 | AD423: =AC423*(1+'Parámetros Proyección'!$E$15) | AE423: =AD423*'Parámetros Proyección'!$F$15 | AF423: =AD423+AE423 | AG423: =IF((AF423/AI423>'Parámetros Proyección'!$G$15),0,D423*'Parámetros Proyección'!$G$15/(IF((H423/AI423>'Parámetros Proyección'!$G$11),0,'Parámetros Proyección'!$G$11)+IF((N423/AI423>'Parámetros Proyección'!$G$12),0,'Parámetros Proyección'!$G$12)+IF((T423/AI423>'Parámetros Proyección'!$G$13),0,'Parámetros Proyección'!$G$13)+IF((Z423/AI423>'Parámetros Proyección'!$G$14),0,'Parámetros Proyección'!$G$14)+IF((AF423/AI423>'Parámetros Proyección'!$G$15),0,'Parámetros Proyección'!$G$15))) | AH423: =AF423+AG423 | AI423: =H423+N423+T423+Z423+AF423 | AJ423: =AF423/AI423 | AK423: =IF(AJ423>'Parámetros Proyección'!$B$5,1,0) | AL423: =G423+M423+S423+Y423+AE423 | AM423: =AM422+D423 | AN423: =AN422+AL423 | AO423: =J423+P423+V423+AB423+AH423

Sheet Proyección Anual
A1: PROYECCIÓN ANUAL (resumen de la hoja 'Proyección Mensual' a fin de cada año)
A2: Inflación asumida (para valor real): | C2: 0.04
A4: Año | B4: Edad | C4: Total CLP | D4: %Div | E4: %USA | F4: %Emerg | G4: %Intl | H4: %Cripto | I4: Aportes acumulados | J4: Dividendos acum. reinv. | K4: Ingreso pasivo anual estimado | L4: Valor real (pesos de hoy)
A5: 2026 | B5: 29 | C5: ='Proyección Mensual'!AO9 | D5: ='Proyección Mensual'!J9/'Proyección Mensual'!AO9 | E5: ='Proyección Mensual'!P9/'Proyección Mensual'!AO9 | F5: ='Proyección Mensual'!V9/'Proyección Mensual'!AO9 | G5: ='Proyección Mensual'!AB9/'Proyección Mensual'!AO9 | H5: ='Proyección Mensual'!AH9/'Proyección Mensual'!AO9 | I5: ='Proyección Mensual'!AM9 | J5: ='Proyección Mensual'!AN9 | K5: ='Proyección Mensual'!J9*'Parámetros Proyección'!$B$11+'Proyección Mensual'!P9*'Parámetros Proyección'!$B$12+'Proyección Mensual'!V9*'Parámetros Proyección'!$B$13+'Proyección Mensual'!AB9*'Parámetros Proyección'!$B$14+'Proyección Mensual'!AH9*'Parámetros Proyección'!$B$15 | L5: =C5/(1+$C$2)^(A5-2026)
A6: 2027 | B6: 30 | C6: ='Proyección Mensual'!AO21 | D6: ='Proyección Mensual'!J21/'Proyección Mensual'!AO21 | E6: ='Proyección Mensual'!P21/'Proyección Mensual'!AO21 | F6: ='Proyección Mensual'!V21/'Proyección Mensual'!AO21 | G6: ='Proyección Mensual'!AB21/'Proyección Mensual'!AO21 | H6: ='Proyección Mensual'!AH21/'Proyección Mensual'!AO21 | I6: ='Proyección Mensual'!AM21 | J6: ='Proyección Mensual'!AN21 | K6: ='Proyección Mensual'!J21*'Parámetros Proyección'!$B$11+'Proyección Mensual'!P21*'Parámetros Proyección'!$B$12+'Proyección Mensual'!V21*'Parámetros Proyección'!$B$13+'Proyección Mensual'!AB21*'Parámetros Proyección'!$B$14+'Proyección Mensual'!AH21*'Parámetros Proyección'!$B$15 | L6: =C6/(1+$C$2)^(A6-2026)
A7: 2028 | B7: 31 | C7: ='Proyección Mensual'!AO33 | D7: ='Proyección Mensual'!J33/'Proyección Mensual'!AO33 | E7: ='Proyección Mensual'!P33/'Proyección Mensual'!AO33 | F7: ='Proyección Mensual'!V33/'Proyección Mensual'!AO33 | G7: ='Proyección Mensual'!AB33/'Proyección Mensual'!AO33 | H7: ='Proyección Mensual'!AH33/'Proyección Mensual'!AO33 | I7: ='Proyección Mensual'!AM33 | J7: ='Proyección Mensual'!AN33 | K7: ='Proyección Mensual'!J33*'Parámetros Proyección'!$B$11+'Proyección Mensual'!P33*'Parámetros Proyección'!$B$12+'Proyección Mensual'!V33*'Parámetros Proyección'!$B$13+'Proyección Mensual'!AB33*'Parámetros Proyección'!$B$14+'Proyección Mensual'!AH33*'Parámetros Proyección'!$B$15 | L7: =C7/(1+$C$2)^(A7-2026)
A8: 2029 | B8: 32 | C8: ='Proyección Mensual'!AO45 | D8: ='Proyección Mensual'!J45/'Proyección Mensual'!AO45 | E8: ='Proyección Mensual'!P45/'Proyección Mensual'!AO45 | F8: ='Proyección Mensual'!V45/'Proyección Mensual'!AO45 | G8: ='Proyección Mensual'!AB45/'Proyección Mensual'!AO45 | H8: ='Proyección Mensual'!AH45/'Proyección Mensual'!AO45 | I8: ='Proyección Mensual'!AM45 | J8: ='Proyección Mensual'!AN45 | K8: ='Proyección Mensual'!J45*'Parámetros Proyección'!$B$11+'Proyección Mensual'!P45*'Parámetros Proyección'!$B$12+'Proyección Mensual'!V45*'Parámetros Proyección'!$B$13+'Proyección Mensual'!AB45*'Parámetros Proyección'!$B$14+'Proyección Mensual'!AH45*'Parámetros Proyección'!$B$15 | L8: =C8/(1+$C$2)^(A8-2026)
A9: 2030 | B9: 33 | C9: ='Proyección Mensual'!AO57 | D9: ='Proyección Mensual'!J57/'Proyección Mensual'!AO57 | E9: ='Proyección Mensual'!P57/'Proyección Mensual'!AO57 | F9: ='Proyección Mensual'!V57/'Proyección Mensual'!AO57 | G9: ='Proyección Mensual'!AB57/'Proyección Mensual'!AO57 | H9: ='Proyección Mensual'!AH57/'Proyección Mensual'!AO57 | I9: ='Proyección Mensual'!AM57 | J9: ='Proyección Mensual'!AN57 | K9: ='Proyección Mensual'!J57*'Parámetros Proyección'!$B$11+'Proyección Mensual'!P57*'Parámetros Proyección'!$B$12+'Proyección Mensual'!V57*'Parámetros Proyección'!$B$13+'Proyección Mensual'!AB57*'Parámetros Proyección'!$B$14+'Proyección Mensual'!AH57*'Parámetros Proyección'!$B$15 | L9: =C9/(1+$C$2)^(A9-2026)
A10: 2031 | B10: 34 | C10: ='Proyección Mensual'!AO69 | D10: ='Proyección Mensual'!J69/'Proyección Mensual'!AO69 | E10: ='Proyección Mensual'!P69/'Proyección Mensual'!AO69 | F10: ='Proyección Mensual'!V69/'Proyección Mensual'!AO69 | G10: ='Proyección Mensual'!AB69/'Proyección Mensual'!AO69 | H10: ='Proyección Mensual'!AH69/'Proyección Mensual'!AO69 | I10: ='Proyección Mensual'!AM69 | J10: ='Proyección Mensual'!AN69 | K10: ='Proyección Mensual'!J69*'Parámetros Proyección'!$B$11+'Proyección Mensual'!P69*'Parámetros Proyección'!$B$12+'Proyección Mensual'!V69*'Parámetros Proyección'!$B$13+'Proyección Mensual'!AB69*'Parámetros Proyección'!$B$14+'Proyección Mensual'!AH69*'Parámetros Proyección'!$B$15 | L10: =C10/(1+$C$2)^(A10-2026)
A11: 2032 | B11: 35 | C11: ='Proyección Mensual'!AO81 | D11: ='Proyección Mensual'!J81/'Proyección Mensual'!AO81 | E11: ='Proyección Mensual'!P81/'Proyección Mensual'!AO81 | F11: ='Proyección Mensual'!V81/'Proyección Mensual'!AO81 | G11: ='Proyección Mensual'!AB81/'Proyección Mensual'!AO81 | H11: ='Proyección Mensual'!AH81/'Proyección Mensual'!AO81 | I11: ='Proyección Mensual'!AM81 | J11: ='Proyección Mensual'!AN81 | K11: ='Proyección Mensual'!J81*'Parámetros Proyección'!$B$11+'Proyección Mensual'!P81*'Parámetros Proyección'!$B$12+'Proyección Mensual'!V81*'Parámetros Proyección'!$B$13+'Proyección Mensual'!AB81*'Parámetros Proyección'!$B$14+'Proyección Mensual'!AH81*'Parámetros Proyección'!$B$15 | L11: =C11/(1+$C$2)^(A11-2026)
A12: 2033 | B12: 36 | C12: ='Proyección Mensual'!AO93 | D12: ='Proyección Mensual'!J93/'Proyección Mensual'!AO93 | E12: ='Proyección Mensual'!P93/'Proyección Mensual'!AO93 | F12: ='Proyección Mensual'!V93/'Proyección Mensual'!AO93 | G12: ='Proyección Mensual'!AB93/'Proyección Mensual'!AO93 | H12: ='Proyección Mensual'!AH93/'Proyección Mensual'!AO93 | I12: ='Proyección Mensual'!AM93 | J12: ='Proyección Mensual'!AN93 | K12: ='Proyección Mensual'!J93*'Parámetros Proyección'!$B$11+'Proyección Mensual'!P93*'Parámetros Proyección'!$B$12+'Proyección Mensual'!V93*'Parámetros Proyección'!$B$13+'Proyección Mensual'!AB93*'Parámetros Proyección'!$B$14+'Proyección Mensual'!AH93*'Parámetros Proyección'!$B$15 | L12: =C12/(1+$C$2)^(A12-2026)
A13: 2034 | B13: 37 | C13: ='Proyección Mensual'!AO105 | D13: ='Proyección Mensual'!J105/'Proyección Mensual'!AO105 | E13: ='Proyección Mensual'!P105/'Proyección Mensual'!AO105 | F13: ='Proyección Mensual'!V105/'Proyección Mensual'!AO105 | G13: ='Proyección Mensual'!AB105/'Proyección Mensual'!AO105 | H13: ='Proyección Mensual'!AH105/'Proyección Mensual'!AO105 | I13: ='Proyección Mensual'!AM105 | J13: ='Proyección Mensual'!AN105 | K13: ='Proyección Mensual'!J105*'Parámetros Proyección'!$B$11+'Proyección Mensual'!P105*'Parámetros Proyección'!$B$12+'Proyección Mensual'!V105*'Parámetros Proyección'!$B$13+'Proyección Mensual'!AB105*'Parámetros Proyección'!$B$14+'Proyección Mensual'!AH105*'Parámetros Proyección'!$B$15 | L13: =C13/(1+$C$2)^(A13-2026)
A14: 2035 | B14: 38 | C14: ='Proyección Mensual'!AO117 | D14: ='Proyección Mensual'!J117/'Proyección Mensual'!AO117 | E14: ='Proyección Mensual'!P117/'Proyección Mensual'!AO117 | F14: ='Proyección Mensual'!V117/'Proyección Mensual'!AO117 | G14: ='Proyección Mensual'!AB117/'Proyección Mensual'!AO117 | H14: ='Proyección Mensual'!AH117/'Proyección Mensual'!AO117 | I14: ='Proyección Mensual'!AM117 | J14: ='Proyección Mensual'!AN117 | K14: ='Proyección Mensual'!J117*'Parámetros Proyección'!$B$11+'Proyección Mensual'!P117*'Parámetros Proyección'!$B$12+'Proyección Mensual'!V117*'Parámetros Proyección'!$B$13+'Proyección Mensual'!AB117*'Parámetros Proyección'!$B$14+'Proyección Mensual'!AH117*'Parámetros Proyección'!$B$15 | L14: =C14/(1+$C$2)^(A14-2026)
A15: 2036 | B15: 39 | C15: ='Proyección Mensual'!AO129 | D15: ='Proyección Mensual'!J129/'Proyección Mensual'!AO129 | E15: ='Proyección Mensual'!P129/'Proyección Mensual'!AO129 | F15: ='Proyección Mensual'!V129/'Proyección Mensual'!AO129 | G15: ='Proyección Mensual'!AB129/'Proyección Mensual'!AO129 | H15: ='Proyección Mensual'!AH129/'Proyección Mensual'!AO129 | I15: ='Proyección Mensual'!AM129 | J15: ='Proyección Mensual'!AN129 | K15: ='Proyección Mensual'!J129*'Parámetros Proyección'!$B$11+'Proyección Mensual'!P129*'Parámetros Proyección'!$B$12+'Proyección Mensual'!V129*'Parámetros Proyección'!$B$13+'Proyección Mensual'!AB129*'Parámetros Proyección'!$B$14+'Proyección Mensual'!AH129*'Parámetros Proyección'!$B$15 | L15: =C15/(1+$C$2)^(A15-2026)
A16: 2037 | B16: 40 | C16: ='Proyección Mensual'!AO141 | D16: ='Proyección Mensual'!J141/'Proyección Mensual'!AO141 | E16: ='Proyección Mensual'!P141/'Proyección Mensual'!AO141 | F16: ='Proyección Mensual'!V141/'Proyección Mensual'!AO141 | G16: ='Proyección Mensual'!AB141/'Proyección Mensual'!AO141 | H16: ='Proyección Mensual'!AH141/'Proyección Mensual'!AO141 | I16: ='Proyección Mensual'!AM141 | J16: ='Proyección Mensual'!AN141 | K16: ='Proyección Mensual'!J141*'Parámetros Proyección'!$B$11+'Proyección Mensual'!P141*'Parámetros Proyección'!$B$12+'Proyección Mensual'!V141*'Parámetros Proyección'!$B$13+'Proyección Mensual'!AB141*'Parámetros Proyección'!$B$14+'Proyección Mensual'!AH141*'Parámetros Proyección'!$B$15 | L16: =C16/(1+$C$2)^(A16-2026)
A17: 2038 | B17: 41 | C17: ='Proyección Mensual'!AO153 | D17: ='Proyección Mensual'!J153/'Proyección Mensual'!AO153 | E17: ='Proyección Mensual'!P153/'Proyección Mensual'!AO153 | F17: ='Proyección Mensual'!V153/'Proyección Mensual'!AO153 | G17: ='Proyección Mensual'!AB153/'Proyección Mensual'!AO153 | H17: ='Proyección Mensual'!AH153/'Proyección Mensual'!AO153 | I17: ='Proyección Mensual'!AM153 | J17: ='Proyección Mensual'!AN153 | K17: ='Proyección Mensual'!J153*'Parámetros Proyección'!$B$11+'Proyección Mensual'!P153*'Parámetros Proyección'!$B$12+'Proyección Mensual'!V153*'Parámetros Proyección'!$B$13+'Proyección Mensual'!AB153*'Parámetros Proyección'!$B$14+'Proyección Mensual'!AH153*'Parámetros Proyección'!$B$15 | L17: =C17/(1+$C$2)^(A17-2026)
A18: 2039 | B18: 42 | C18: ='Proyección Mensual'!AO165 | D18: ='Proyección Mensual'!J165/'Proyección Mensual'!AO165 | E18: ='Proyección Mensual'!P165/'Proyección Mensual'!AO165 | F18: ='Proyección Mensual'!V165/'Proyección Mensual'!AO165 | G18: ='Proyección Mensual'!AB165/'Proyección Mensual'!AO165 | H18: ='Proyección Mensual'!AH165/'Proyección Mensual'!AO165 | I18: ='Proyección Mensual'!AM165 | J18: ='Proyección Mensual'!AN165 | K18: ='Proyección Mensual'!J165*'Parámetros Proyección'!$B$11+'Proyección Mensual'!P165*'Parámetros Proyección'!$B$12+'Proyección Mensual'!V165*'Parámetros Proyección'!$B$13+'Proyección Mensual'!AB165*'Parámetros Proyección'!$B$14+'Proyección Mensual'!AH165*'Parámetros Proyección'!$B$15 | L18: =C18/(1+$C$2)^(A18-2026)
A19: 2040 | B19: 43 | C19: ='Proyección Mensual'!AO177 | D19: ='Proyección Mensual'!J177/'Proyección Mensual'!AO177 | E19: ='Proyección Mensual'!P177/'Proyección Mensual'!AO177 | F19: ='Proyección Mensual'!V177/'Proyección Mensual'!AO177 | G19: ='Proyección Mensual'!AB177/'Proyección Mensual'!AO177 | H19: ='Proyección Mensual'!AH177/'Proyección Mensual'!AO177 | I19: ='Proyección Mensual'!AM177 | J19: ='Proyección Mensual'!AN177 | K19: ='Proyección Mensual'!J177*'Parámetros Proyección'!$B$11+'Proyección Mensual'!P177*'Parámetros Proyección'!$B$12+'Proyección Mensual'!V177*'Parámetros Proyección'!$B$13+'Proyección Mensual'!AB177*'Parámetros Proyección'!$B$14+'Proyección Mensual'!AH177*'Parámetros Proyección'!$B$15 | L19: =C19/(1+$C$2)^(A19-2026)
A20: 2041 | B20: 44 | C20: ='Proyección Mensual'!AO189 | D20: ='Proyección Mensual'!J189/'Proyección Mensual'!AO189 | E20: ='Proyección Mensual'!P189/'Proyección Mensual'!AO189 | F20: ='Proyección Mensual'!V189/'Proyección Mensual'!AO189 | G20: ='Proyección Mensual'!AB189/'Proyección Mensual'!AO189 | H20: ='Proyección Mensual'!AH189/'Proyección Mensual'!AO189 | I20: ='Proyección Mensual'!AM189 | J20: ='Proyección Mensual'!AN189 | K20: ='Proyección Mensual'!J189*'Parámetros Proyección'!$B$11+'Proyección Mensual'!P189*'Parámetros Proyección'!$B$12+'Proyección Mensual'!V189*'Parámetros Proyección'!$B$13+'Proyección Mensual'!AB189*'Parámetros Proyección'!$B$14+'Proyección Mensual'!AH189*'Parámetros Proyección'!$B$15 | L20: =C20/(1+$C$2)^(A20-2026)
A21: 2042 | B21: 45 | C21: ='Proyección Mensual'!AO201 | D21: ='Proyección Mensual'!J201/'Proyección Mensual'!AO201 | E21: ='Proyección Mensual'!P201/'Proyección Mensual'!AO201 | F21: ='Proyección Mensual'!V201/'Proyección Mensual'!AO201 | G21: ='Proyección Mensual'!AB201/'Proyección Mensual'!AO201 | H21: ='Proyección Mensual'!AH201/'Proyección Mensual'!AO201 | I21: ='Proyección Mensual'!AM201 | J21: ='Proyección Mensual'!AN201 | K21: ='Proyección Mensual'!J201*'Parámetros Proyección'!$B$11+'Proyección Mensual'!P201*'Parámetros Proyección'!$B$12+'Proyección Mensual'!V201*'Parámetros Proyección'!$B$13+'Proyección Mensual'!AB201*'Parámetros Proyección'!$B$14+'Proyección Mensual'!AH201*'Parámetros Proyección'!$B$15 | L21: =C21/(1+$C$2)^(A21-2026)
A22: 2043 | B22: 46 | C22: ='Proyección Mensual'!AO213 | D22: ='Proyección Mensual'!J213/'Proyección Mensual'!AO213 | E22: ='Proyección Mensual'!P213/'Proyección Mensual'!AO213 | F22: ='Proyección Mensual'!V213/'Proyección Mensual'!AO213 | G22: ='Proyección Mensual'!AB213/'Proyección Mensual'!AO213 | H22: ='Proyección Mensual'!AH213/'Proyección Mensual'!AO213 | I22: ='Proyección Mensual'!AM213 | J22: ='Proyección Mensual'!AN213 | K22: ='Proyección Mensual'!J213*'Parámetros Proyección'!$B$11+'Proyección Mensual'!P213*'Parámetros Proyección'!$B$12+'Proyección Mensual'!V213*'Parámetros Proyección'!$B$13+'Proyección Mensual'!AB213*'Parámetros Proyección'!$B$14+'Proyección Mensual'!AH213*'Parámetros Proyección'!$B$15 | L22: =C22/(1+$C$2)^(A22-2026)
A23: 2044 | B23: 47 | C23: ='Proyección Mensual'!AO225 | D23: ='Proyección Mensual'!J225/'Proyección Mensual'!AO225 | E23: ='Proyección Mensual'!P225/'Proyección Mensual'!AO225 | F23: ='Proyección Mensual'!V225/'Proyección Mensual'!AO225 | G23: ='Proyección Mensual'!AB225/'Proyección Mensual'!AO225 | H23: ='Proyección Mensual'!AH225/'Proyección Mensual'!AO225 | I23: ='Proyección Mensual'!AM225 | J23: ='Proyección Mensual'!AN225 | K23: ='Proyección Mensual'!J225*'Parámetros Proyección'!$B$11+'Proyección Mensual'!P225*'Parámetros Proyección'!$B$12+'Proyección Mensual'!V225*'Parámetros Proyección'!$B$13+'Proyección Mensual'!AB225*'Parámetros Proyección'!$B$14+'Proyección Mensual'!AH225*'Parámetros Proyección'!$B$15 | L23: =C23/(1+$C$2)^(A23-2026)
A24: 2045 | B24: 48 | C24: ='Proyección Mensual'!AO237 | D24: ='Proyección Mensual'!J237/'Proyección Mensual'!AO237 | E24: ='Proyección Mensual'!P237/'Proyección Mensual'!AO237 | F24: ='Proyección Mensual'!V237/'Proyección Mensual'!AO237 | G24: ='Proyección Mensual'!AB237/'Proyección Mensual'!AO237 | H24: ='Proyección Mensual'!AH237/'Proyección Mensual'!AO237 | I24: ='Proyección Mensual'!AM237 | J24: ='Proyección Mensual'!AN237 | K24: ='Proyección Mensual'!J237*'Parámetros Proyección'!$B$11+'Proyección Mensual'!P237*'Parámetros Proyección'!$B$12+'Proyección Mensual'!V237*'Parámetros Proyección'!$B$13+'Proyección Mensual'!AB237*'Parámetros Proyección'!$B$14+'Proyección Mensual'!AH237*'Parámetros Proyección'!$B$15 | L24: =C24/(1+$C$2)^(A24-2026)
A25: 2046 | B25: 49 | C25: ='Proyección Mensual'!AO249 | D25: ='Proyección Mensual'!J249/'Proyección Mensual'!AO249 | E25: ='Proyección Mensual'!P249/'Proyección Mensual'!AO249 | F25: ='Proyección Mensual'!V249/'Proyección Mensual'!AO249 | G25: ='Proyección Mensual'!AB249/'Proyección Mensual'!AO249 | H25: ='Proyección Mensual'!AH249/'Proyección Mensual'!AO249 | I25: ='Proyección Mensual'!AM249 | J25: ='Proyección Mensual'!AN249 | K25: ='Proyección Mensual'!J249*'Parámetros Proyección'!$B$11+'Proyección Mensual'!P249*'Parámetros Proyección'!$B$12+'Proyección Mensual'!V249*'Parámetros Proyección'!$B$13+'Proyección Mensual'!AB249*'Parámetros Proyección'!$B$14+'Proyección Mensual'!AH249*'Parámetros Proyección'!$B$15 | L25: =C25/(1+$C$2)^(A25-2026)
A26: 2047 | B26: 50 | C26: ='Proyección Mensual'!AO261 | D26: ='Proyección Mensual'!J261/'Proyección Mensual'!AO261 | E26: ='Proyección Mensual'!P261/'Proyección Mensual'!AO261 | F26: ='Proyección Mensual'!V261/'Proyección Mensual'!AO261 | G26: ='Proyección Mensual'!AB261/'Proyección Mensual'!AO261 | H26: ='Proyección Mensual'!AH261/'Proyección Mensual'!AO261 | I26: ='Proyección Mensual'!AM261 | J26: ='Proyección Mensual'!AN261 | K26: ='Proyección Mensual'!J261*'Parámetros Proyección'!$B$11+'Proyección Mensual'!P261*'Parámetros Proyección'!$B$12+'Proyección Mensual'!V261*'Parámetros Proyección'!$B$13+'Proyección Mensual'!AB261*'Parámetros Proyección'!$B$14+'Proyección Mensual'!AH261*'Parámetros Proyección'!$B$15 | L26: =C26/(1+$C$2)^(A26-2026)
A27: 2048 | B27: 51 | C27: ='Proyección Mensual'!AO273 | D27: ='Proyección Mensual'!J273/'Proyección Mensual'!AO273 | E27: ='Proyección Mensual'!P273/'Proyección Mensual'!AO273 | F27: ='Proyección Mensual'!V273/'Proyección Mensual'!AO273 | G27: ='Proyección Mensual'!AB273/'Proyección Mensual'!AO273 | H27: ='Proyección Mensual'!AH273/'Proyección Mensual'!AO273 | I27: ='Proyección Mensual'!AM273 | J27: ='Proyección Mensual'!AN273 | K27: ='Proyección Mensual'!J273*'Parámetros Proyección'!$B$11+'Proyección Mensual'!P273*'Parámetros Proyección'!$B$12+'Proyección Mensual'!V273*'Parámetros Proyección'!$B$13+'Proyección Mensual'!AB273*'Parámetros Proyección'!$B$14+'Proyección Mensual'!AH273*'Parámetros Proyección'!$B$15 | L27: =C27/(1+$C$2)^(A27-2026)
A28: 2049 | B28: 52 | C28: ='Proyección Mensual'!AO285 | D28: ='Proyección Mensual'!J285/'Proyección Mensual'!AO285 | E28: ='Proyección Mensual'!P285/'Proyección Mensual'!AO285 | F28: ='Proyección Mensual'!V285/'Proyección Mensual'!AO285 | G28: ='Proyección Mensual'!AB285/'Proyección Mensual'!AO285 | H28: ='Proyección Mensual'!AH285/'Proyección Mensual'!AO285 | I28: ='Proyección Mensual'!AM285 | J28: ='Proyección Mensual'!AN285 | K28: ='Proyección Mensual'!J285*'Parámetros Proyección'!$B$11+'Proyección Mensual'!P285*'Parámetros Proyección'!$B$12+'Proyección Mensual'!V285*'Parámetros Proyección'!$B$13+'Proyección Mensual'!AB285*'Parámetros Proyección'!$B$14+'Proyección Mensual'!AH285*'Parámetros Proyección'!$B$15 | L28: =C28/(1+$C$2)^(A28-2026)
A29: 2050 | B29: 53 | C29: ='Proyección Mensual'!AO297 | D29: ='Proyección Mensual'!J297/'Proyección Mensual'!AO297 | E29: ='Proyección Mensual'!P297/'Proyección Mensual'!AO297 | F29: ='Proyección Mensual'!V297/'Proyección Mensual'!AO297 | G29: ='Proyección Mensual'!AB297/'Proyección Mensual'!AO297 | H29: ='Proyección Mensual'!AH297/'Proyección Mensual'!AO297 | I29: ='Proyección Mensual'!AM297 | J29: ='Proyección Mensual'!AN297 | K29: ='Proyección Mensual'!J297*'Parámetros Proyección'!$B$11+'Proyección Mensual'!P297*'Parámetros Proyección'!$B$12+'Proyección Mensual'!V297*'Parámetros Proyección'!$B$13+'Proyección Mensual'!AB297*'Parámetros Proyección'!$B$14+'Proyección Mensual'!AH297*'Parámetros Proyección'!$B$15 | L29: =C29/(1+$C$2)^(A29-2026)
A30: 2051 | B30: 54 | C30: ='Proyección Mensual'!AO309 | D30: ='Proyección Mensual'!J309/'Proyección Mensual'!AO309 | E30: ='Proyección Mensual'!P309/'Proyección Mensual'!AO309 | F30: ='Proyección Mensual'!V309/'Proyección Mensual'!AO309 | G30: ='Proyección Mensual'!AB309/'Proyección Mensual'!AO309 | H30: ='Proyección Mensual'!AH309/'Proyección Mensual'!AO309 | I30: ='Proyección Mensual'!AM309 | J30: ='Proyección Mensual'!AN309 | K30: ='Proyección Mensual'!J309*'Parámetros Proyección'!$B$11+'Proyección Mensual'!P309*'Parámetros Proyección'!$B$12+'Proyección Mensual'!V309*'Parámetros Proyección'!$B$13+'Proyección Mensual'!AB309*'Parámetros Proyección'!$B$14+'Proyección Mensual'!AH309*'Parámetros Proyección'!$B$15 | L30: =C30/(1+$C$2)^(A30-2026)
A31: 2052 | B31: 55 | C31: ='Proyección Mensual'!AO321 | D31: ='Proyección Mensual'!J321/'Proyección Mensual'!AO321 | E31: ='Proyección Mensual'!P321/'Proyección Mensual'!AO321 | F31: ='Proyección Mensual'!V321/'Proyección Mensual'!AO321 | G31: ='Proyección Mensual'!AB321/'Proyección Mensual'!AO321 | H31: ='Proyección Mensual'!AH321/'Proyección Mensual'!AO321 | I31: ='Proyección Mensual'!AM321 | J31: ='Proyección Mensual'!AN321 | K31: ='Proyección Mensual'!J321*'Parámetros Proyección'!$B$11+'Proyección Mensual'!P321*'Parámetros Proyección'!$B$12+'Proyección Mensual'!V321*'Parámetros Proyección'!$B$13+'Proyección Mensual'!AB321*'Parámetros Proyección'!$B$14+'Proyección Mensual'!AH321*'Parámetros Proyección'!$B$15 | L31: =C31/(1+$C$2)^(A31-2026)
A32: 2053 | B32: 56 | C32: ='Proyección Mensual'!AO333 | D32: ='Proyección Mensual'!J333/'Proyección Mensual'!AO333 | E32: ='Proyección Mensual'!P333/'Proyección Mensual'!AO333 | F32: ='Proyección Mensual'!V333/'Proyección Mensual'!AO333 | G32: ='Proyección Mensual'!AB333/'Proyección Mensual'!AO333 | H32: ='Proyección Mensual'!AH333/'Proyección Mensual'!AO333 | I32: ='Proyección Mensual'!AM333 | J32: ='Proyección Mensual'!AN333 | K32: ='Proyección Mensual'!J333*'Parámetros Proyección'!$B$11+'Proyección Mensual'!P333*'Parámetros Proyección'!$B$12+'Proyección Mensual'!V333*'Parámetros Proyección'!$B$13+'Proyección Mensual'!AB333*'Parámetros Proyección'!$B$14+'Proyección Mensual'!AH333*'Parámetros Proyección'!$B$15 | L32: =C32/(1+$C$2)^(A32-2026)
A33: 2054 | B33: 57 | C33: ='Proyección Mensual'!AO345 | D33: ='Proyección Mensual'!J345/'Proyección Mensual'!AO345 | E33: ='Proyección Mensual'!P345/'Proyección Mensual'!AO345 | F33: ='Proyección Mensual'!V345/'Proyección Mensual'!AO345 | G33: ='Proyección Mensual'!AB345/'Proyección Mensual'!AO345 | H33: ='Proyección Mensual'!AH345/'Proyección Mensual'!AO345 | I33: ='Proyección Mensual'!AM345 | J33: ='Proyección Mensual'!AN345 | K33: ='Proyección Mensual'!J345*'Parámetros Proyección'!$B$11+'Proyección Mensual'!P345*'Parámetros Proyección'!$B$12+'Proyección Mensual'!V345*'Parámetros Proyección'!$B$13+'Proyección Mensual'!AB345*'Parámetros Proyección'!$B$14+'Proyección Mensual'!AH345*'Parámetros Proyección'!$B$15 | L33: =C33/(1+$C$2)^(A33-2026)
A34: 2055 | B34: 58 | C34: ='Proyección Mensual'!AO357 | D34: ='Proyección Mensual'!J357/'Proyección Mensual'!AO357 | E34: ='Proyección Mensual'!P357/'Proyección Mensual'!AO357 | F34: ='Proyección Mensual'!V357/'Proyección Mensual'!AO357 | G34: ='Proyección Mensual'!AB357/'Proyección Mensual'!AO357 | H34: ='Proyección Mensual'!AH357/'Proyección Mensual'!AO357 | I34: ='Proyección Mensual'!AM357 | J34: ='Proyección Mensual'!AN357 | K34: ='Proyección Mensual'!J357*'Parámetros Proyección'!$B$11+'Proyección Mensual'!P357*'Parámetros Proyección'!$B$12+'Proyección Mensual'!V357*'Parámetros Proyección'!$B$13+'Proyección Mensual'!AB357*'Parámetros Proyección'!$B$14+'Proyección Mensual'!AH357*'Parámetros Proyección'!$B$15 | L34: =C34/(1+$C$2)^(A34-2026)
A35: 2056 | B35: 59 | C35: ='Proyección Mensual'!AO369 | D35: ='Proyección Mensual'!J369/'Proyección Mensual'!AO369 | E35: ='Proyección Mensual'!P369/'Proyección Mensual'!AO369 | F35: ='Proyección Mensual'!V369/'Proyección Mensual'!AO369 | G35: ='Proyección Mensual'!AB369/'Proyección Mensual'!AO369 | H35: ='Proyección Mensual'!AH369/'Proyección Mensual'!AO369 | I35: ='Proyección Mensual'!AM369 | J35: ='Proyección Mensual'!AN369 | K35: ='Proyección Mensual'!J369*'Parámetros Proyección'!$B$11+'Proyección Mensual'!P369*'Parámetros Proyección'!$B$12+'Proyección Mensual'!V369*'Parámetros Proyección'!$B$13+'Proyección Mensual'!AB369*'Parámetros Proyección'!$B$14+'Proyección Mensual'!AH369*'Parámetros Proyección'!$B$15 | L35: =C35/(1+$C$2)^(A35-2026)
A36: 2057 | B36: 60 | C36: ='Proyección Mensual'!AO381 | D36: ='Proyección Mensual'!J381/'Proyección Mensual'!AO381 | E36: ='Proyección Mensual'!P381/'Proyección Mensual'!AO381 | F36: ='Proyección Mensual'!V381/'Proyección Mensual'!AO381 | G36: ='Proyección Mensual'!AB381/'Proyección Mensual'!AO381 | H36: ='Proyección Mensual'!AH381/'Proyección Mensual'!AO381 | I36: ='Proyección Mensual'!AM381 | J36: ='Proyección Mensual'!AN381 | K36: ='Proyección Mensual'!J381*'Parámetros Proyección'!$B$11+'Proyección Mensual'!P381*'Parámetros Proyección'!$B$12+'Proyección Mensual'!V381*'Parámetros Proyección'!$B$13+'Proyección Mensual'!AB381*'Parámetros Proyección'!$B$14+'Proyección Mensual'!AH381*'Parámetros Proyección'!$B$15 | L36: =C36/(1+$C$2)^(A36-2026)
A37: 2058 | B37: 61 | C37: ='Proyección Mensual'!AO393 | D37: ='Proyección Mensual'!J393/'Proyección Mensual'!AO393 | E37: ='Proyección Mensual'!P393/'Proyección Mensual'!AO393 | F37: ='Proyección Mensual'!V393/'Proyección Mensual'!AO393 | G37: ='Proyección Mensual'!AB393/'Proyección Mensual'!AO393 | H37: ='Proyección Mensual'!AH393/'Proyección Mensual'!AO393 | I37: ='Proyección Mensual'!AM393 | J37: ='Proyección Mensual'!AN393 | K37: ='Proyección Mensual'!J393*'Parámetros Proyección'!$B$11+'Proyección Mensual'!P393*'Parámetros Proyección'!$B$12+'Proyección Mensual'!V393*'Parámetros Proyección'!$B$13+'Proyección Mensual'!AB393*'Parámetros Proyección'!$B$14+'Proyección Mensual'!AH393*'Parámetros Proyección'!$B$15 | L37: =C37/(1+$C$2)^(A37-2026)
A38: 2059 | B38: 62 | C38: ='Proyección Mensual'!AO405 | D38: ='Proyección Mensual'!J405/'Proyección Mensual'!AO405 | E38: ='Proyección Mensual'!P405/'Proyección Mensual'!AO405 | F38: ='Proyección Mensual'!V405/'Proyección Mensual'!AO405 | G38: ='Proyección Mensual'!AB405/'Proyección Mensual'!AO405 | H38: ='Proyección Mensual'!AH405/'Proyección Mensual'!AO405 | I38: ='Proyección Mensual'!AM405 | J38: ='Proyección Mensual'!AN405 | K38: ='Proyección Mensual'!J405*'Parámetros Proyección'!$B$11+'Proyección Mensual'!P405*'Parámetros Proyección'!$B$12+'Proyección Mensual'!V405*'Parámetros Proyección'!$B$13+'Proyección Mensual'!AB405*'Parámetros Proyección'!$B$14+'Proyección Mensual'!AH405*'Parámetros Proyección'!$B$15 | L38: =C38/(1+$C$2)^(A38-2026)
A39: 2060 | B39: 63 | C39: ='Proyección Mensual'!AO417 | D39: ='Proyección Mensual'!J417/'Proyección Mensual'!AO417 | E39: ='Proyección Mensual'!P417/'Proyección Mensual'!AO417 | F39: ='Proyección Mensual'!V417/'Proyección Mensual'!AO417 | G39: ='Proyección Mensual'!AB417/'Proyección Mensual'!AO417 | H39: ='Proyección Mensual'!AH417/'Proyección Mensual'!AO417 | I39: ='Proyección Mensual'!AM417 | J39: ='Proyección Mensual'!AN417 | K39: ='Proyección Mensual'!J417*'Parámetros Proyección'!$B$11+'Proyección Mensual'!P417*'Parámetros Proyección'!$B$12+'Proyección Mensual'!V417*'Parámetros Proyección'!$B$13+'Proyección Mensual'!AB417*'Parámetros Proyección'!$B$14+'Proyección Mensual'!AH417*'Parámetros Proyección'!$B$15 | L39: =C39/(1+$C$2)^(A39-2026)
A41: Nota: la fila resaltada (2057) es el año en que cumples 60 años (15/02/2057).
A42: Cambia cualquier supuesto en 'Parámetros Proyección' y esta tabla se recalcula sola.
